verif/rtl/test_ram_sync.v
// test_ram_sync_fixed.v
// Same as test_ram_sync.v but with hardcoded widths (no module parameters),
// so Yosys does not mangle the module into a \$paramod$<hash>\ram_sync name.
// This keeps the mapped netlist's identifiers plain and parser-friendly.

module ram_sync (
    input  wire         clk,
    input  wire         we,
    input  wire [3:0]   wbyte_en,
    input  wire [12:0]  waddr,
    input  wire [31:0]  wdata,
    input  wire         re,
    input  wire [12:0]  raddr,
    output reg  [31:0]  rdata
);

    reg [31:0] mem [0:8191];

    always @(posedge clk) begin
        if (we) begin
            if (wbyte_en[0]) mem[waddr][7:0]   <= wdata[7:0];
            if (wbyte_en[1]) mem[waddr][15:8]  <= wdata[15:8];
            if (wbyte_en[2]) mem[waddr][23:16] <= wdata[23:16];
            if (wbyte_en[3]) mem[waddr][31:24] <= wdata[31:24];
        end
    end

    always @(posedge clk) begin
        if (re)
            rdata <= mem[raddr];
    end

endmodule


module top (
    input  wire        clk,
    input  wire        we,
    input  wire [3:0]  wbyte_en,
    input  wire [12:0] waddr,
    input  wire [31:0] wdata,
    input  wire        re,
    input  wire [12:0] raddr,
    output wire [31:0] rdata
);

    ram_sync u_ram (
        .clk      (clk),
        .we       (we),
        .wbyte_en (wbyte_en),
        .waddr    (waddr),
        .wdata    (wdata),
        .re       (re),
        .raddr    (raddr),
        .rdata    (rdata)
    );

endmodule

verif/sim_out/gem_cuda_output.vcd
$timescale 1 ps $end
$scope module top $end
$var wire 1 ! rdata[31] $end
$var wire 1 " rdata[30] $end
$var wire 1 # rdata[29] $end
$var wire 1 $ rdata[28] $end
$var wire 1 % rdata[27] $end
$var wire 1 & rdata[26] $end
$var wire 1 ' rdata[25] $end
$var wire 1 ( rdata[24] $end
$var wire 1 ) rdata[23] $end
$var wire 1 * rdata[22] $end
$var wire 1 + rdata[21] $end
$var wire 1 , rdata[20] $end
$var wire 1 - rdata[19] $end
$var wire 1 . rdata[18] $end
$var wire 1 / rdata[17] $end
$var wire 1 0 rdata[16] $end
$var wire 1 1 rdata[15] $end
$var wire 1 2 rdata[14] $end
$var wire 1 3 rdata[13] $end
$var wire 1 4 rdata[12] $end
$var wire 1 5 rdata[11] $end
$var wire 1 6 rdata[10] $end
$var wire 1 7 rdata[9] $end
$var wire 1 8 rdata[8] $end
$var wire 1 9 rdata[7] $end
$var wire 1 : rdata[6] $end
$var wire 1 ; rdata[5] $end
$var wire 1 < rdata[4] $end
$var wire 1 = rdata[3] $end
$var wire 1 > rdata[2] $end
$var wire 1 ? rdata[1] $end
$var wire 1 @ rdata[0] $end
$upscope $end
$enddefinitions $end
$dumpvars
#0
0!
0"
0#
0$
0%
0&
0'
0(
0)
0*
0+
0,
0-
0.
0/
00
01
02
03
04
05
06
07
08
09
0:
0;
0<
0=
0>
0?
0@
#5000
#15000
#25000
#35000
1!
1"
1$
1%
1&
1'
1)
1+
1-
1.
10
11
13
14
15
16
17
19
1:
1;
1=
1>
1?
1@
#45000
#55000
#65000
#75000
0!
0"
0%
0&
0)
1,
0-
00
01
12
03
05
09
1<
0>
0?
0@
#85000
#95000
1!
1"
1%
1&
1)
0,
1-
10
11
02
13
15
19
0<
1>
1?
1@
#105000
#115000
#125000
#135000
0:
0>
0@
#145000
#155000
#165000
#175000
1#
1(
#185000
#195000
#205000
#215000
#225000
#235000
#245000
#255000
#265000
#275000
#285000
#295000
#305000
#315000
#325000
#335000
#345000
#355000
0"
0$
0%
0&
0'
0(
0)
0+
0-
0.
00
01
03
04
05
06
07
09
0;
0=
0?
#365000
#375000
1@
#385000
#395000
1?
0@
#405000
#415000
1@
#425000
#435000
1>
0?
0@
#445000
#455000
1@
#465000
#475000
1?
0@
#485000
#495000
1@
#505000
#515000
#525000
#535000
1"
0#
1%
1'
1)
1*
1+
1,
1-
1.
1/
11
12
13
14
1=
0?
