verif/rtl/test_ram_sync.v
// test_ram_sync_fixed.v
// Same as test_ram_sync.v but with hardcoded widths (no module parameters),
// so Yosys does not mangle the module into a \$paramod$<hash>\ram_sync name.
// This keeps the mapped netlist's identifiers plain and parser-friendly.

module ram_sync (
    input  wire         clk,
    input  wire         we,
    input  wire [3:0]   wbyte_en,
    input  wire [12:0]  waddr,
    input  wire [31:0]  wdata,
    input  wire         re,
    input  wire [12:0]  raddr,
    output reg  [31:0]  rdata
);

    reg [31:0] mem [0:8191];

    always @(posedge clk) begin
        if (we) begin
            if (wbyte_en[0]) mem[waddr][7:0]   <= wdata[7:0];
            if (wbyte_en[1]) mem[waddr][15:8]  <= wdata[15:8];
            if (wbyte_en[2]) mem[waddr][23:16] <= wdata[23:16];
            if (wbyte_en[3]) mem[waddr][31:24] <= wdata[31:24];
        end
    end

    always @(posedge clk) begin
        if (re)
            rdata <= mem[raddr];
    end

endmodule


module top (
    input  wire        clk,
    input  wire        we,
    input  wire [3:0]  wbyte_en,
    input  wire [12:0] waddr,
    input  wire [31:0] wdata,
    input  wire        re,
    input  wire [12:0] raddr,
    output wire [31:0] rdata
);

    ram_sync u_ram (
        .clk      (clk),
        .we       (we),
        .wbyte_en (wbyte_en),
        .waddr    (waddr),
        .wdata    (wdata),
        .re       (re),
        .raddr    (raddr),
        .rdata    (rdata)
    );

endmodule

verif/tb/tb_stimulus.v
// tb_stimulus.v
// Generates the INPUT_VCD for `naive_sim NETLIST_VERILOG INPUT_VCD OUTPUT_VCD`.
//
// Runs the exact same stimulus sequence as tb_ram_sync.v, but against the
// ORIGINAL (pre-Yosys) RTL, and dumps the VCD scoped to the `top` instance
// only. Because this VCD is captured from the real (golden) RTL, it
// contains both:
//   - the input waveforms (clk, we, wbyte_en, waddr, wdata, re, raddr)
//     which naive_sim will replay against the mapped netlist, and
//   - the golden `rdata` waveform, which you diff naive_sim's OUTPUT_VCD
//     against afterward.
//
// IMPORTANT: the dumped scope is named `top` to match the top module name
// in memory_mapped_sync.v, so naive_sim can line up signal paths between
// the two files. If GEM's naive_sim expects a different scope/hierarchy
// convention (e.g. dumping at the testbench root instead of the DUT
// instance), adjust the $dumpvars scope accordingly -- check `naive_sim
// --help` or its source for the exact VCD hierarchy it expects.

`timescale 1ns/1ps

module tb_stimulus;

    reg         clk;
    reg         we;
    reg  [3:0]  wbyte_en;
    reg  [12:0] waddr;
    reg  [31:0] wdata;
    reg         re;
    reg  [12:0] raddr;
    wire [31:0] rdata;

    integer i;

    top dut (
        .clk      (clk),
        .we       (we),
        .wbyte_en (wbyte_en),
        .waddr    (waddr),
        .wdata    (wdata),
        .re       (re),
        .raddr    (raddr),
        .rdata    (rdata)
    );

    always #5 clk = ~clk;

    task do_write(input [12:0] a, input [31:0] d, input [3:0] be);
        begin
            @(negedge clk);
            we       = 1;
            wbyte_en = be;
            waddr    = a;
            wdata    = d;
            @(negedge clk);
            we       = 0;
        end
    endtask

    task do_read(input [12:0] a);
        begin
            @(negedge clk);
            re    = 1;
            raddr = a;
            @(negedge clk);
            re    = 0;
        end
    endtask

    initial begin
        clk      = 0;
        we       = 0;
        wbyte_en = 4'b0000;
        waddr    = 0;
        wdata    = 0;
        re       = 0;
        raddr    = 0;

        // identical sequence to tb_ram_sync.v, minus the self-check logic
        do_write(13'd10, 32'hDEADBEEF, 4'b1111);
        do_read(13'd10);

        do_write(13'd20, 32'h12345678, 4'b1111);
        do_read(13'd20);
        do_read(13'd10);

        do_write(13'd10, 32'h000000AA, 4'b0001);
        do_read(13'd10);

        do_write(13'd10, 32'hFF000000, 4'b1000);
        do_read(13'd10);

        for (i = 0; i < 8; i = i + 1)
            do_write(i, 32'hA000_0000 + i, 4'b1111);
        for (i = 0; i < 8; i = i + 1)
            do_read(i);

        do_write(13'd8191, 32'hCAFEF00D, 4'b1111);
        do_read(13'd8191);

        #20;
        $display("STIMULUS DONE");
        $finish;
    end

    initial begin
        $dumpfile("stim_and_golden.vcd");
        $dumpvars(0, dut);   // scope = `top` instance, matches mapped netlist's top module
    end

endmodule

verif/sim_out/stim_and_golden.vcd
$date
	Fri Aug 28 20:49:44 2026
$end
$version
	Icarus Verilog
$end
$timescale
	1ps
$end
$scope module tb_stimulus $end
$scope module dut $end
$var wire 1 ! clk $end
$var wire 13 " raddr [12:0] $end
$var wire 1 # re $end
$var wire 13 $ waddr [12:0] $end
$var wire 4 % wbyte_en [3:0] $end
$var wire 32 & wdata [31:0] $end
$var wire 1 ' we $end
$var wire 32 ( rdata [31:0] $end
$scope module u_ram $end
$var wire 1 ! clk $end
$var wire 13 ) raddr [12:0] $end
$var wire 1 # re $end
$var wire 13 * waddr [12:0] $end
$var wire 4 + wbyte_en [3:0] $end
$var wire 32 , wdata [31:0] $end
$var wire 1 ' we $end
$var reg 32 - rdata [31:0] $end
$upscope $end
$upscope $end
$upscope $end
$enddefinitions $end
$comment Show the parameter values. $end
$dumpall
$end
#0
$dumpvars
bx -
b0 ,
b0 +
b0 *
b0 )
bx (
0'
b0 &
b0 %
b0 $
0#
b0 "
0!
$end
#5000
1!
#10000
b11011110101011011011111011101111 &
b11011110101011011011111011101111 ,
b1010 $
b1010 *
b1111 %
b1111 +
1'
0!
#15000
1!
#20000
0'
0!
#25000
1!
#30000
b1010 "
b1010 )
1#
0!
#35000
b11011110101011011011111011101111 (
b11011110101011011011111011101111 -
1!
#40000
0#
0!
#45000
1!
#50000
b10010001101000101011001111000 &
b10010001101000101011001111000 ,
b10100 $
b10100 *
1'
0!
#55000
1!
#60000
0'
0!
#65000
1!
#70000
b10100 "
b10100 )
1#
0!
#75000
b10010001101000101011001111000 (
b10010001101000101011001111000 -
1!
#80000
0#
0!
#85000
1!
#90000
b1010 "
b1010 )
1#
0!
#95000
b11011110101011011011111011101111 (
b11011110101011011011111011101111 -
1!
#100000
0#
0!
#105000
1!
#110000
b10101010 &
b10101010 ,
b1010 $
b1010 *
b1 %
b1 +
1'
0!
#115000
1!
#120000
0'
0!
#125000
1!
#130000
1#
0!
#135000
b11011110101011011011111010101010 (
b11011110101011011011111010101010 -
1!
#140000
0#
0!
#145000
1!
#150000
b11111111000000000000000000000000 &
b11111111000000000000000000000000 ,
b1000 %
b1000 +
1'
0!
#155000
1!
#160000
0'
0!
#165000
1!
#170000
1#
0!
#175000
b11111111101011011011111010101010 (
b11111111101011011011111010101010 -
1!
#180000
0#
0!
#185000
1!
#190000
b10100000000000000000000000000000 &
b10100000000000000000000000000000 ,
b0 $
b0 *
b1111 %
b1111 +
1'
0!
#195000
1!
#200000
0'
0!
#205000
1!
#210000
b10100000000000000000000000000001 &
b10100000000000000000000000000001 ,
b1 $
b1 *
1'
0!
#215000
1!
#220000
0'
0!
#225000
1!
#230000
b10100000000000000000000000000010 &
b10100000000000000000000000000010 ,
b10 $
b10 *
1'
0!
#235000
1!
#240000
0'
0!
#245000
1!
#250000
b10100000000000000000000000000011 &
b10100000000000000000000000000011 ,
b11 $
b11 *
1'
0!
#255000
1!
#260000
0'
0!
#265000
1!
#270000
b10100000000000000000000000000100 &
b10100000000000000000000000000100 ,
b100 $
b100 *
1'
0!
#275000
1!
#280000
0'
0!
#285000
1!
#290000
b10100000000000000000000000000101 &
b10100000000000000000000000000101 ,
b101 $
b101 *
1'
0!
#295000
1!
#300000
0'
0!
#305000
1!
#310000
b10100000000000000000000000000110 &
b10100000000000000000000000000110 ,
b110 $
b110 *
1'
0!
#315000
1!
#320000
0'
0!
#325000
1!
#330000
b10100000000000000000000000000111 &
b10100000000000000000000000000111 ,
b111 $
b111 *
1'
0!
#335000
1!
#340000
0'
0!
#345000
1!
#350000
b0 "
b0 )
1#
0!
#355000
b10100000000000000000000000000000 (
b10100000000000000000000000000000 -
1!
#360000
0#
0!
#365000
1!
#370000
b1 "
b1 )
1#
0!
#375000
b10100000000000000000000000000001 (
b10100000000000000000000000000001 -
1!
#380000
0#
0!
#385000
1!
#390000
b10 "
b10 )
1#
0!
#395000
b10100000000000000000000000000010 (
b10100000000000000000000000000010 -
1!
#400000
0#
0!
#405000
1!
#410000
b11 "
b11 )
1#
0!
#415000
b10100000000000000000000000000011 (
b10100000000000000000000000000011 -
1!
#420000
0#
0!
#425000
1!
#430000
b100 "
b100 )
1#
0!
#435000
b10100000000000000000000000000100 (
b10100000000000000000000000000100 -
1!
#440000
0#
0!
#445000
1!
#450000
b101 "
b101 )
1#
0!
#455000
b10100000000000000000000000000101 (
b10100000000000000000000000000101 -
1!
#460000
0#
0!
#465000
1!
#470000
b110 "
b110 )
1#
0!
#475000
b10100000000000000000000000000110 (
b10100000000000000000000000000110 -
1!
#480000
0#
0!
#485000
1!
#490000
b111 "
b111 )
1#
0!
#495000
b10100000000000000000000000000111 (
b10100000000000000000000000000111 -
1!
#500000
0#
0!
#505000
1!
#510000
b11001010111111101111000000001101 &
b11001010111111101111000000001101 ,
b1111111111111 $
b1111111111111 *
1'
0!
#515000
1!
#520000
0'
0!
#525000
1!
#530000
b1111111111111 "
b1111111111111 )
1#
0!
#535000
b11001010111111101111000000001101 (
b11001010111111101111000000001101 -
1!
#540000
0#
0!
