build/gemdiff/xilinx_macros_ref.v
// ===========================================================================
// CROSS-CHECK AGAINST PUBLIC XILINX FUNCTIONAL DOCUMENTATION
// ===========================================================================
// These are clean-room models written from documented functional behaviour.
// No UNISIM source was consulted or copied; UNISIM is proprietary and is not
// present in this environment.
//
// Document mapping (CONFIRMED):
//   UG579 - UltraScale Architecture DSP Slice User Guide  -> DSP48E2   <== ours
//   UG479 - 7 Series DSP48E1 Slice User Guide             -> DSP48E1  (NOT ours)
//   UG474 - 7 Series FPGAs Configurable Logic Block Guide -> CARRY4, SRLC32E
//
// The problem statement targets DSP48E2, so UG579 is the applicable DSP guide.
// UG479 covers the older DSP48E1 and does NOT describe our target part.
//
// ---------------------------------------------------------------------------
// DSP48E2: deviations of THIS MODEL from full silicon, all spec-mandated
// ---------------------------------------------------------------------------
// Matches documented DSP48E2 behaviour:
//   - 27x18 signed multiplier producing a 45-bit product
//   - 48-bit P accumulator register
//   - 27-bit pre-adder whose sum wraps at 27 bits
//   - D port 27 bits, B port 18 bits, C port 48 bits
//
// Deliberate simplifications imposed by the problem statement:
//   1. A PORT WIDTH. Real DSP48E2 has a 30-bit A port (A[29:0]); only the low
//      27 bits reach the pre-adder, while the full width feeds the A:B
//      concatenation path. The problem statement fixes A at 27 bits, so this
//      model uses 27. Anything relying on A[29:27] is out of scope.
//   2. PRE-ADDER. Real silicon computes D +/- A under INMODE control. The
//      statement fixes AD = A + D (addition only), or A passed through.
//   3. OPMODE/ALUMODE. Real silicon selects the datapath with a 9-bit OPMODE
//      plus a 4-bit ALUMODE. The statement replaces both with a 2-bit state:
//      0 = P<=C, 1 = P<=M, 2 = P<=P+M.
//   4. PIPELINE REGISTERS. AREG=BREG=CREG=DREG=ADREG=MREG=0, PREG=1.
//   5. NOT MODELLED: PCIN/PCOUT cascade, CARRYIN/CARRYCASCIN/CARRYOUT,
//      pattern detector, SIMD modes, wide XOR, and the OVERFLOW/UNDERFLOW
//      pins (the statement explicitly puts OVERFLOW/UNDERFLOW out of scope).
//
// ---------------------------------------------------------------------------
// CARRY4: agrees with UG474 with no simplification
// ---------------------------------------------------------------------------
//   UG474 describes the carry chain as, per bit i:
//       O[i]  = S[i] XOR C[i]
//       C[i+1] = S[i] ? C[i] : DI[i]
//   The mux form S ? C : DI is Boolean-identical to the form used here,
//   (S & C) | (~S & DI), so the two descriptions agree exactly.
//   CYINIT initialises the bottom CARRY4 of a chain; CIN carries the cascade
//   into every later block. Exactly one is active in valid RTL, which is why
//   C[0] = CYINIT | CIN is a faithful encoding rather than a shortcut.
//
// ---------------------------------------------------------------------------
// SRLC32E: agrees with UG474 apart from INIT
// ---------------------------------------------------------------------------
//   32-bit shift register, CE-gated, shifting on the rising clock edge;
//   Q reads the bit selected by the 5-bit address A; Q31 is the fixed bit-31
//   cascade output used to chain SRLs together.
//   Deviation: the real primitive takes an INIT parameter for initial
//   contents. The problem statement puts INIT parsing out of scope, so the
//   register always starts at zero here.
// ===========================================================================

// SPDX-License-Identifier: Apache-2.0
// Behavioural golden models for the three Xilinx primitives GEM must
// evaluate natively.
//
// These are written to be as LITERAL a transcription of the problem
// statement's equations as possible -- in particular CARRY4_ref is a genuine
// four-step ripple, and carry_chain_ref really does daisy-chain CO[3] into
// the next block's CI. They are intentionally NOT clever.
//
// The point of that is independence: csrc/gem_macros.cuh evaluates a fused
// carry chain as a single 64-bit add, and the whole verification argument is
// that the clever version and this literal version agree on random vectors.
// If both files shared an optimisation, the test would prove nothing.

`timescale 1ns / 1ps

// ---------------------------------------------------------------------------
// CARRY4 -- literal transcription of the silicon equations
// ---------------------------------------------------------------------------
//   C[0]   = CYINIT | CI
//   C[i+1] = (S[i] & C[i]) | (~S[i] & DI[i])
//   O[i]   = S[i] ^ C[i]
//   CO[i]  = C[i+1]
module CARRY4_ref (
    output [3:0] CO,
    output [3:0] O,
    input        CI,
    input        CYINIT,
    input  [3:0] DI,
    input  [3:0] S
);
    wire [4:0] C;
    assign C[0] = CYINIT | CI;

    genvar i;
    generate
        for (i = 0; i < 4; i = i + 1) begin : gen_bit
            assign C[i+1] = (S[i] & C[i]) | (~S[i] & DI[i]);
            assign O[i]   = S[i] ^ C[i];
            assign CO[i]  = C[i+1];
        end
    endgenerate
endmodule

// ---------------------------------------------------------------------------
// A cascade of NBLK CARRY4s, wired CO[3] -> CI exactly as a synthesiser would
// emit for a wide adder. This is the structure GEM must recognise and fuse.
// ---------------------------------------------------------------------------
module carry_chain_ref #(
    parameter NBLK = 15
) (
    output [4*NBLK-1:0] O,
    output [4*NBLK-1:0] CO,
    input               CYINIT,
    input  [4*NBLK-1:0] DI,
    input  [4*NBLK-1:0] S
);
    wire [NBLK:0] cc;
    assign cc[0] = 1'b0;

    genvar b;
    generate
        for (b = 0; b < NBLK; b = b + 1) begin : gen_blk
            CARRY4_ref u_c4 (
                .CO     (CO[4*b+3 -: 4]),
                .O      (O [4*b+3 -: 4]),
                // Block 0 takes the chain initialiser on CYINIT; every later
                // block takes the previous block's CO[3] on CI. Only one of
                // the two is ever active, per the problem statement.
                .CI     ((b == 0) ? 1'b0   : cc[b]),
                .CYINIT ((b == 0) ? CYINIT : 1'b0),
                .DI     (DI[4*b+3 -: 4]),
                .S      (S [4*b+3 -: 4])
            );
            assign cc[b+1] = CO[4*b+3];
        end
    endgenerate
endmodule

// ---------------------------------------------------------------------------
// DSP48E2 simplified subset
// ---------------------------------------------------------------------------
// AREG/BREG/CREG/DREG/ADREG/MREG = 0 (combinational), PREG = 1 (clocked).
//   AD     = use_pre ? A + D : A      (wraps at 27 bits)
//   M      = AD * B                   (45-bit signed)
//   P_next = state==0 ? C : state==1 ? M : P + M
module dsp48e2_ref (
    output reg signed [47:0] P,
    input                    clk,
    input      signed [26:0] A,
    input      signed [26:0] D,
    input      signed [17:0] B,
    input      signed [47:0] C,
    input             [1:0]  state,
    input                    use_pre
);
    // 27-bit pre-adder: the sum truncates back to 27 bits.
    wire signed [26:0] AD = use_pre ? (A + D) : A;
    // 27 x 18 -> 45 bit signed product.
    wire signed [44:0] M  = AD * B;

    reg signed [47:0] p_next;
    always @(*) begin
        case (state)
            2'd0:    p_next = C;        // bypass
            2'd1:    p_next = M;        // multiply only
            default: p_next = P + M;    // multiply-accumulate
        endcase
    end

    initial P = 48'd0;                  // registers initialise to zero
    always @(posedge clk) P <= p_next;
endmodule

// ---------------------------------------------------------------------------
// SRLC32E shift register LUT
// ---------------------------------------------------------------------------
//   on posedge, if CE: state <= {state[30:0], D}   (shift LSB -> MSB)
//   Q   = state[A]    combinational, dynamic address
//   Q31 = state[31]   combinational cascade output
module srlc32e_ref (
    output       Q,
    output       Q31,
    input        clk,
    input        CE,
    input        D,
    input  [4:0] A
);
    reg [31:0] state;
    initial state = 32'd0;              // registers initialise to zero

    assign Q   = state[A];
    assign Q31 = state[31];

    always @(posedge clk) begin
        if (CE) state <= {state[30:0], D};
    end
endmodule

build/gemdiff/tb_carry4.v
// Differential testbench: CARRY4 slice + cascaded carry chain.
// Reads stimulus vectors, writes results for comparison against the Python
// golden model. Purely combinational -- no clock.
`timescale 1ns/1ps
`include "xilinx_macros_ref.v"

module tb_carry4;
    localparam NBLK = 15;              // 60-bit chain
    localparam NBIT = 4*NBLK;

    // --- single slice ---
    reg  [3:0] S, DI;
    reg        CIN, CYINIT;
    wire [3:0] O, CO;
    CARRY4_ref u_slice (.CO(CO), .O(O), .CI(CIN), .CYINIT(CYINIT), .DI(DI), .S(S));

    // --- cascaded chain ---
    reg  [NBIT-1:0] cS, cDI;
    reg             cCYINIT;
    wire [NBIT-1:0] cO, cCO;
    carry_chain_ref #(.NBLK(NBLK)) u_chain
        (.O(cO), .CO(cCO), .CYINIT(cCYINIT), .DI(cDI), .S(cS));

    integer fi, fo, n;

    // Waveform capture for inspection. Written under sim_out/,
    // never the repo root.
    initial begin
        $dumpfile("sim_out/tb_carry4.vcd");
        $dumpvars(0, tb_carry4);
    end

    initial begin
        // ---- slice vectors ----
        fi = $fopen("sim_out/stim_carry4.txt", "r");
        fo = $fopen("sim_out/res_carry4.txt", "w");
        if (fi == 0 || fo == 0) begin $display("FILE ERROR"); $finish; end
        n = $fscanf(fi, "%h %h %h %h\n", S, DI, CIN, CYINIT);
        while (n == 4) begin
            #1;
            $fdisplay(fo, "%h %h", O, CO);
            n = $fscanf(fi, "%h %h %h %h\n", S, DI, CIN, CYINIT);
        end
        $fclose(fi); $fclose(fo);

        // ---- chain vectors ----
        fi = $fopen("sim_out/stim_chain.txt", "r");
        fo = $fopen("sim_out/res_chain.txt", "w");
        if (fi == 0 || fo == 0) begin $display("FILE ERROR"); $finish; end
        n = $fscanf(fi, "%h %h %h\n", cS, cDI, cCYINIT);
        while (n == 3) begin
            #1;
            $fdisplay(fo, "%h %h", cO, cCO);
            n = $fscanf(fi, "%h %h %h\n", cS, cDI, cCYINIT);
        end
        $fclose(fi); $fclose(fo);
        $finish;
    end
endmodule

build/gemdiff/sim_out/tb_carry4.vcd
$date
	Wed Aug 26 20:51:45 2026
$end
$version
	Icarus Verilog
$end
$timescale
	1ps
$end
$scope module tb_carry4 $end
$var wire 60 ! cO [59:0] $end
$var wire 60 " cCO [59:0] $end
$var wire 4 # O [3:0] $end
$var wire 4 $ CO [3:0] $end
$var parameter 64 % NBIT $end
$var parameter 32 & NBLK $end
$var reg 1 ' CIN $end
$var reg 1 ( CYINIT $end
$var reg 4 ) DI [3:0] $end
$var reg 4 * S [3:0] $end
$var reg 1 + cCYINIT $end
$var reg 60 , cDI [59:0] $end
$var reg 60 - cS [59:0] $end
$var integer 32 . fi [31:0] $end
$var integer 32 / fo [31:0] $end
$var integer 32 0 n [31:0] $end
$scope module u_chain $end
$var wire 1 + CYINIT $end
$var wire 60 1 DI [59:0] $end
$var wire 60 2 S [59:0] $end
$var wire 16 3 cc [15:0] $end
$var wire 60 4 O [59:0] $end
$var wire 60 5 CO [59:0] $end
$var parameter 32 6 NBLK $end
$scope begin gen_blk[0] $end
$var parameter 2 7 b $end
$scope module u_c4 $end
$var wire 1 8 CI $end
$var wire 1 + CYINIT $end
$var wire 4 9 DI [3:0] $end
$var wire 4 : S [3:0] $end
$var wire 4 ; O [3:0] $end
$var wire 4 < CO [3:0] $end
$var wire 5 = C [4:0] $end
$scope begin gen_bit[0] $end
$var parameter 2 > i $end
$upscope $end
$scope begin gen_bit[1] $end
$var parameter 2 ? i $end
$upscope $end
$scope begin gen_bit[2] $end
$var parameter 3 @ i $end
$upscope $end
$scope begin gen_bit[3] $end
$var parameter 3 A i $end
$upscope $end
$upscope $end
$upscope $end
$scope begin gen_blk[1] $end
$var parameter 2 B b $end
$scope module u_c4 $end
$var wire 1 C CI $end
$var wire 1 D CYINIT $end
$var wire 4 E DI [3:0] $end
$var wire 4 F S [3:0] $end
$var wire 4 G O [3:0] $end
$var wire 4 H CO [3:0] $end
$var wire 5 I C [4:0] $end
$scope begin gen_bit[0] $end
$var parameter 2 J i $end
$upscope $end
$scope begin gen_bit[1] $end
$var parameter 2 K i $end
$upscope $end
$scope begin gen_bit[2] $end
$var parameter 3 L i $end
$upscope $end
$scope begin gen_bit[3] $end
$var parameter 3 M i $end
$upscope $end
$upscope $end
$upscope $end
$scope begin gen_blk[2] $end
$var parameter 3 N b $end
$scope module u_c4 $end
$var wire 1 O CI $end
$var wire 1 P CYINIT $end
$var wire 4 Q DI [3:0] $end
$var wire 4 R S [3:0] $end
$var wire 4 S O [3:0] $end
$var wire 4 T CO [3:0] $end
$var wire 5 U C [4:0] $end
$scope begin gen_bit[0] $end
$var parameter 2 V i $end
$upscope $end
$scope begin gen_bit[1] $end
$var parameter 2 W i $end
$upscope $end
$scope begin gen_bit[2] $end
$var parameter 3 X i $end
$upscope $end
$scope begin gen_bit[3] $end
$var parameter 3 Y i $end
$upscope $end
$upscope $end
$upscope $end
$scope begin gen_blk[3] $end
$var parameter 3 Z b $end
$scope module u_c4 $end
$var wire 1 [ CI $end
$var wire 1 \ CYINIT $end
$var wire 4 ] DI [3:0] $end
$var wire 4 ^ S [3:0] $end
$var wire 4 _ O [3:0] $end
$var wire 4 ` CO [3:0] $end
$var wire 5 a C [4:0] $end
$scope begin gen_bit[0] $end
$var parameter 2 b i $end
$upscope $end
$scope begin gen_bit[1] $end
$var parameter 2 c i $end
$upscope $end
$scope begin gen_bit[2] $end
$var parameter 3 d i $end
$upscope $end
$scope begin gen_bit[3] $end
$var parameter 3 e i $end
$upscope $end
$upscope $end
$upscope $end
$scope begin gen_blk[4] $end
$var parameter 4 f b $end
$scope module u_c4 $end
$var wire 1 g CI $end
$var wire 1 h CYINIT $end
$var wire 4 i DI [3:0] $end
$var wire 4 j S [3:0] $end
$var wire 4 k O [3:0] $end
$var wire 4 l CO [3:0] $end
$var wire 5 m C [4:0] $end
$scope begin gen_bit[0] $end
$var parameter 2 n i $end
$upscope $end
$scope begin gen_bit[1] $end
$var parameter 2 o i $end
$upscope $end
$scope begin gen_bit[2] $end
$var parameter 3 p i $end
$upscope $end
$scope begin gen_bit[3] $end
$var parameter 3 q i $end
$upscope $end
$upscope $end
$upscope $end
$scope begin gen_blk[5] $end
$var parameter 4 r b $end
$scope module u_c4 $end
$var wire 1 s CI $end
$var wire 1 t CYINIT $end
$var wire 4 u DI [3:0] $end
$var wire 4 v S [3:0] $end
$var wire 4 w O [3:0] $end
$var wire 4 x CO [3:0] $end
$var wire 5 y C [4:0] $end
$scope begin gen_bit[0] $end
$var parameter 2 z i $end
$upscope $end
$scope begin gen_bit[1] $end
$var parameter 2 { i $end
$upscope $end
$scope begin gen_bit[2] $end
$var parameter 3 | i $end
$upscope $end
$scope begin gen_bit[3] $end
$var parameter 3 } i $end
$upscope $end
$upscope $end
$upscope $end
$scope begin gen_blk[6] $end
$var parameter 4 ~ b $end
$scope module u_c4 $end
$var wire 1 !" CI $end
$var wire 1 "" CYINIT $end
$var wire 4 #" DI [3:0] $end
$var wire 4 $" S [3:0] $end
$var wire 4 %" O [3:0] $end
$var wire 4 &" CO [3:0] $end
$var wire 5 '" C [4:0] $end
$scope begin gen_bit[0] $end
$var parameter 2 (" i $end
$upscope $end
$scope begin gen_bit[1] $end
$var parameter 2 )" i $end
$upscope $end
$scope begin gen_bit[2] $end
$var parameter 3 *" i $end
$upscope $end
$scope begin gen_bit[3] $end
$var parameter 3 +" i $end
$upscope $end
$upscope $end
$upscope $end
$scope begin gen_blk[7] $end
$var parameter 4 ," b $end
$scope module u_c4 $end
$var wire 1 -" CI $end
$var wire 1 ." CYINIT $end
$var wire 4 /" DI [3:0] $end
$var wire 4 0" S [3:0] $end
$var wire 4 1" O [3:0] $end
$var wire 4 2" CO [3:0] $end
$var wire 5 3" C [4:0] $end
$scope begin gen_bit[0] $end
$var parameter 2 4" i $end
$upscope $end
$scope begin gen_bit[1] $end
$var parameter 2 5" i $end
$upscope $end
$scope begin gen_bit[2] $end
$var parameter 3 6" i $end
$upscope $end
$scope begin gen_bit[3] $end
$var parameter 3 7" i $end
$upscope $end
$upscope $end
$upscope $end
$scope begin gen_blk[8] $end
$var parameter 5 8" b $end
$scope module u_c4 $end
$var wire 1 9" CI $end
$var wire 1 :" CYINIT $end
$var wire 4 ;" DI [3:0] $end
$var wire 4 <" S [3:0] $end
$var wire 4 =" O [3:0] $end
$var wire 4 >" CO [3:0] $end
$var wire 5 ?" C [4:0] $end
$scope begin gen_bit[0] $end
$var parameter 2 @" i $end
$upscope $end
$scope begin gen_bit[1] $end
$var parameter 2 A" i $end
$upscope $end
$scope begin gen_bit[2] $end
$var parameter 3 B" i $end
$upscope $end
$scope begin gen_bit[3] $end
$var parameter 3 C" i $end
$upscope $end
$upscope $end
$upscope $end
$scope begin gen_blk[9] $end
$var parameter 5 D" b $end
$scope module u_c4 $end
$var wire 1 E" CI $end
$var wire 1 F" CYINIT $end
$var wire 4 G" DI [3:0] $end
$var wire 4 H" S [3:0] $end
$var wire 4 I" O [3:0] $end
$var wire 4 J" CO [3:0] $end
$var wire 5 K" C [4:0] $end
$scope begin gen_bit[0] $end
$var parameter 2 L" i $end
$upscope $end
$scope begin gen_bit[1] $end
$var parameter 2 M" i $end
$upscope $end
$scope begin gen_bit[2] $end
$var parameter 3 N" i $end
$upscope $end
$scope begin gen_bit[3] $end
$var parameter 3 O" i $end
$upscope $end
$upscope $end
$upscope $end
$scope begin gen_blk[10] $end
$var parameter 5 P" b $end
$scope module u_c4 $end
$var wire 1 Q" CI $end
$var wire 1 R" CYINIT $end
$var wire 4 S" DI [3:0] $end
$var wire 4 T" S [3:0] $end
$var wire 4 U" O [3:0] $end
$var wire 4 V" CO [3:0] $end
$var wire 5 W" C [4:0] $end
$scope begin gen_bit[0] $end
$var parameter 2 X" i $end
$upscope $end
$scope begin gen_bit[1] $end
$var parameter 2 Y" i $end
$upscope $end
$scope begin gen_bit[2] $end
$var parameter 3 Z" i $end
$upscope $end
$scope begin gen_bit[3] $end
$var parameter 3 [" i $end
$upscope $end
$upscope $end
$upscope $end
$scope begin gen_blk[11] $end
$var parameter 5 \" b $end
$scope module u_c4 $end
$var wire 1 ]" CI $end
$var wire 1 ^" CYINIT $end
$var wire 4 _" DI [3:0] $end
$var wire 4 `" S [3:0] $end
$var wire 4 a" O [3:0] $end
$var wire 4 b" CO [3:0] $end
$var wire 5 c" C [4:0] $end
$scope begin gen_bit[0] $end
$var parameter 2 d" i $end
$upscope $end
$scope begin gen_bit[1] $end
$var parameter 2 e" i $end
$upscope $end
$scope begin gen_bit[2] $end
$var parameter 3 f" i $end
$upscope $end
$scope begin gen_bit[3] $end
$var parameter 3 g" i $end
$upscope $end
$upscope $end
$upscope $end
$scope begin gen_blk[12] $end
$var parameter 5 h" b $end
$scope module u_c4 $end
$var wire 1 i" CI $end
$var wire 1 j" CYINIT $end
$var wire 4 k" DI [3:0] $end
$var wire 4 l" S [3:0] $end
$var wire 4 m" O [3:0] $end
$var wire 4 n" CO [3:0] $end
$var wire 5 o" C [4:0] $end
$scope begin gen_bit[0] $end
$var parameter 2 p" i $end
$upscope $end
$scope begin gen_bit[1] $end
$var parameter 2 q" i $end
$upscope $end
$scope begin gen_bit[2] $end
$var parameter 3 r" i $end
$upscope $end
$scope begin gen_bit[3] $end
$var parameter 3 s" i $end
$upscope $end
$upscope $end
$upscope $end
$scope begin gen_blk[13] $end
$var parameter 5 t" b $end
$scope module u_c4 $end
$var wire 1 u" CI $end
$var wire 1 v" CYINIT $end
$var wire 4 w" DI [3:0] $end
$var wire 4 x" S [3:0] $end
$var wire 4 y" O [3:0] $end
$var wire 4 z" CO [3:0] $end
$var wire 5 {" C [4:0] $end
$scope begin gen_bit[0] $end
$var parameter 2 |" i $end
$upscope $end
$scope begin gen_bit[1] $end
$var parameter 2 }" i $end
$upscope $end
$scope begin gen_bit[2] $end
$var parameter 3 ~" i $end
$upscope $end
$scope begin gen_bit[3] $end
$var parameter 3 !# i $end
$upscope $end
$upscope $end
$upscope $end
$scope begin gen_blk[14] $end
$var parameter 5 "# b $end
$scope module u_c4 $end
$var wire 1 ## CI $end
$var wire 1 $# CYINIT $end
$var wire 4 %# DI [3:0] $end
$var wire 4 &# S [3:0] $end
$var wire 4 '# O [3:0] $end
$var wire 4 (# CO [3:0] $end
$var wire 5 )# C [4:0] $end
$scope begin gen_bit[0] $end
$var parameter 2 *# i $end
$upscope $end
$scope begin gen_bit[1] $end
$var parameter 2 +# i $end
$upscope $end
$scope begin gen_bit[2] $end
$var parameter 3 ,# i $end
$upscope $end
$scope begin gen_bit[3] $end
$var parameter 3 -# i $end
$upscope $end
$upscope $end
$upscope $end
$upscope $end
$scope module u_slice $end
$var wire 1 ' CI $end
$var wire 1 ( CYINIT $end
$var wire 4 .# DI [3:0] $end
$var wire 4 /# S [3:0] $end
$var wire 4 0# O [3:0] $end
$var wire 4 1# CO [3:0] $end
$var wire 5 2# C [4:0] $end
$scope begin gen_bit[0] $end
$var parameter 2 3# i $end
$upscope $end
$scope begin gen_bit[1] $end
$var parameter 2 4# i $end
$upscope $end
$scope begin gen_bit[2] $end
$var parameter 3 5# i $end
$upscope $end
$scope begin gen_bit[3] $end
$var parameter 3 6# i $end
$upscope $end
$upscope $end
$upscope $end
$enddefinitions $end
$comment Show the parameter values. $end
$dumpall
b11 6#
b10 5#
b1 4#
b0 3#
b11 -#
b10 ,#
b1 +#
b0 *#
b1110 "#
b11 !#
b10 ~"
b1 }"
b0 |"
b1101 t"
b11 s"
b10 r"
b1 q"
b0 p"
b1100 h"
b11 g"
b10 f"
b1 e"
b0 d"
b1011 \"
b11 ["
b10 Z"
b1 Y"
b0 X"
b1010 P"
b11 O"
b10 N"
b1 M"
b0 L"
b1001 D"
b11 C"
b10 B"
b1 A"
b0 @"
b1000 8"
b11 7"
b10 6"
b1 5"
b0 4"
b111 ,"
b11 +"
b10 *"
b1 )"
b0 ("
b110 ~
b11 }
b10 |
b1 {
b0 z
b101 r
b11 q
b10 p
b1 o
b0 n
b100 f
b11 e
b10 d
b1 c
b0 b
b11 Z
b11 Y
b10 X
b1 W
b0 V
b10 N
b11 M
b10 L
b1 K
b0 J
b1 B
b11 A
b10 @
b1 ?
b0 >
b0 7
b1111 6
b1111 &
b111100 %
$end
#0
$dumpvars
b0 2#
b0 1#
b0 0#
b0 /#
b0 .#
bx )#
bx (#
bx '#
bx &#
bx %#
0$#
x##
bx {"
bx z"
bx y"
bx x"
bx w"
0v"
xu"
bx o"
bx n"
bx m"
bx l"
bx k"
0j"
xi"
bx c"
bx b"
bx a"
bx `"
bx _"
0^"
x]"
bx W"
bx V"
bx U"
bx T"
bx S"
0R"
xQ"
bx K"
bx J"
bx I"
bx H"
bx G"
0F"
xE"
bx ?"
bx >"
bx ="
bx <"
bx ;"
0:"
x9"
bx 3"
bx 2"
bx 1"
bx 0"
bx /"
0."
x-"
bx '"
bx &"
bx %"
bx $"
bx #"
0""
x!"
bx y
bx x
bx w
bx v
bx u
0t
xs
bx m
bx l
bx k
bx j
bx i
0h
xg
bx a
bx `
bx _
bx ^
bx ]
0\
x[
bx U
bx T
bx S
bx R
bx Q
0P
xO
bx I
bx H
bx G
bx F
bx E
0D
xC
bx =
bx <
bx ;
bx :
bx 9
08
bx 5
bx 4
bx0 3
bx 2
bx 1
b100 0
b10000000000000000000000000000100 /
b10000000000000000000000000000011 .
bx -
bx ,
x+
b0 *
b0 )
0(
0'
b0 $
b0 #
bx "
bx !
$end
#1000
b1 #
b1 0#
b1 2#
1(
#2000
0(
1'
#3000
1(
#4000
b1111 $
b1111 1#
b1110 #
b1110 0#
b11110 2#
0(
0'
b1111 )
b1111 .#
#5000
b1111 #
b1111 0#
b11111 2#
1(
#6000
0(
1'
#7000
1(
#8000
b1010 $
b1010 1#
b100 #
b100 0#
b10100 2#
0(
0'
b1010 )
b1010 .#
#9000
b101 #
b101 0#
b10101 2#
1(
#10000
0(
1'
#11000
1(
#12000
b101 $
b101 1#
b1010 #
b1010 0#
b1010 2#
0(
0'
b101 )
b101 .#
#13000
b1011 #
b1011 0#
b1011 2#
1(
#14000
0(
1'
#15000
1(
#16000
b0 $
b0 1#
b1111 #
b1111 0#
b0 2#
0(
0'
b0 )
b0 .#
b1111 *
b1111 /#
#17000
b1111 $
b1111 1#
b0 #
b0 0#
b11111 2#
1(
#18000
0(
1'
#19000
1(
#20000
b0 $
b0 1#
b1111 #
b1111 0#
b0 2#
0(
0'
b1111 )
b1111 .#
#21000
b1111 $
b1111 1#
b0 #
b0 0#
b11111 2#
1(
#22000
0(
1'
#23000
1(
#24000
b0 $
b0 1#
b1111 #
b1111 0#
b0 2#
0(
0'
b1010 )
b1010 .#
#25000
b1111 $
b1111 1#
b0 #
b0 0#
b11111 2#
1(
#26000
0(
1'
#27000
1(
#28000
b0 $
b0 1#
b1111 #
b1111 0#
b0 2#
0(
0'
b101 )
b101 .#
#29000
b1111 $
b1111 1#
b0 #
b0 0#
b11111 2#
1(
#30000
0(
1'
#31000
1(
#32000
b0 $
b0 1#
b1010 #
b1010 0#
b0 2#
0(
0'
b0 )
b0 .#
b1010 *
b1010 /#
#33000
b1011 #
b1011 0#
b1 2#
1(
#34000
0(
1'
#35000
1(
#36000
b1111 $
b1111 1#
b100 #
b100 0#
b11110 2#
0(
0'
b1111 )
b1111 .#
#37000
b101 #
b101 0#
b11111 2#
1(
#38000
0(
1'
#39000
1(
#40000
b0 $
b0 1#
b1010 #
b1010 0#
b0 2#
0(
0'
b1010 )
b1010 .#
#41000
b1011 #
b1011 0#
b1 2#
1(
#42000
0(
1'
#43000
1(
#44000
b1111 $
b1111 1#
b100 #
b100 0#
b11110 2#
0(
0'
b101 )
b101 .#
#45000
b101 #
b101 0#
b11111 2#
1(
#46000
0(
1'
#47000
1(
#48000
b0 $
b0 1#
b101 #
b101 0#
b0 2#
0(
0'
b0 )
b0 .#
b101 *
b101 /#
#49000
b1 $
b1 1#
b110 #
b110 0#
b11 2#
1(
#50000
0(
1'
#51000
1(
#52000
b1110 $
b1110 1#
b1001 #
b1001 0#
b11100 2#
0(
0'
b1111 )
b1111 .#
#53000
b1111 $
b1111 1#
b1010 #
b1010 0#
b11111 2#
1(
#54000
0(
1'
#55000
1(
#56000
b1110 $
b1110 1#
b1001 #
b1001 0#
b11100 2#
0(
0'
b1010 )
b1010 .#
#57000
b1111 $
b1111 1#
b1010 #
b1010 0#
b11111 2#
1(
#58000
0(
1'
#59000
1(
#60000
b0 $
b0 1#
b101 #
b101 0#
b0 2#
0(
0'
b101 )
b101 .#
#61000
b1 $
b1 1#
b110 #
b110 0#
b11 2#
1(
#62000
0(
1'
#63000
1(
#64000
b0 $
b0 1#
b1 #
b1 0#
b0 2#
0(
0'
b0 )
b0 .#
b1 *
b1 /#
#65000
b1 $
b1 1#
b10 #
b10 0#
b11 2#
1(
#66000
0(
1'
#67000
1(
#68000
b1110 $
b1110 1#
b1101 #
b1101 0#
b11100 2#
0(
0'
b1111 )
b1111 .#
#69000
b1111 $
b1111 1#
b1110 #
b1110 0#
b11111 2#
1(
#70000
0(
1'
#71000
1(
#72000
b1010 $
b1010 1#
b101 #
b101 0#
b10100 2#
0(
0'
b1010 )
b1010 .#
#73000
b1011 $
b1011 1#
b110 #
b110 0#
b10111 2#
1(
#74000
0(
1'
#75000
1(
#76000
b100 $
b100 1#
b1001 #
b1001 0#
b1000 2#
0(
0'
b101 )
b101 .#
#77000
b101 $
b101 1#
b1010 #
b1010 0#
b1011 2#
1(
#78000
0(
1'
#79000
1(
#80000
b0 $
b0 1#
b1000 #
b1000 0#
b0 2#
0(
0'
b0 )
b0 .#
b1000 *
b1000 /#
#81000
b1001 #
b1001 0#
b1 2#
1(
#82000
0(
1'
#83000
1(
#84000
b1111 $
b1111 1#
b110 #
b110 0#
b11110 2#
0(
0'
b1111 )
b1111 .#
#85000
b111 #
b111 0#
b11111 2#
1(
#86000
0(
1'
#87000
1(
#88000
b10 $
b10 1#
b1100 #
b1100 0#
b100 2#
0(
0'
b1010 )
b1010 .#
#89000
b1101 #
b1101 0#
b101 2#
1(
#90000
0(
1'
#91000
1(
#92000
b1101 $
b1101 1#
b10 #
b10 0#
b11010 2#
0(
0'
b101 )
b101 .#
#93000
b11 #
b11 0#
b11011 2#
1(
#94000
0(
1'
#95000
1(
#96000
b1 #
b1 0#
b1100 $
b1100 1#
b11001 2#
0'
b1100 )
b1100 .#
#97000
b10 $
b10 1#
b1101 #
b1101 0#
b100 2#
0(
b11 )
b11 .#
b1001 *
b1001 /#
#98000
b1100 #
b1100 0#
b1010 )
b1010 .#
b1000 *
b1000 /#
#99000
b1000 $
b1000 1#
b111 #
b111 0#
b10001 2#
1'
b1000 )
b1000 .#
b110 *
b110 /#
#100000
b11 $
b11 1#
b100 #
b100 0#
b110 2#
0'
b11 )
b11 .#
b10 *
b10 /#
#101000
b1101 #
b1101 0#
b111 2#
1(
b1010 *
b1010 /#
#102000
b111 $
b111 1#
b1111 2#
b1111 #
b1111 0#
1'
b111 )
b111 .#
b0 *
b0 /#
#103000
b1111 $
b1111 1#
b11111 2#
b1100 #
b1100 0#
b1110 )
b1110 .#
b11 *
b11 /#
#104000
b1110 $
b1110 1#
b11101 2#
b1 #
b1 0#
b110 )
b110 .#
b1100 *
b1100 /#
#105000
b0 $
b0 1#
b1 2#
b1011 #
b1011 0#
0(
b1000 )
b1000 .#
b1010 *
b1010 /#
#106000
b1110 $
b1110 1#
b11101 2#
b1101 #
b1101 0#
1(
0'
b1110 )
b1110 .#
b0 *
b0 /#
#107000
b1 #
b1 0#
0(
1'
b110 )
b110 .#
b1100 *
b1100 /#
#108000
b1111 $
b1111 1#
b11111 2#
b1101 #
b1101 0#
1(
0'
b1111 )
b1111 .#
b10 *
b10 /#
#109000
b111 $
b111 1#
b1111 2#
b1010 #
b1010 0#
b10 )
b10 .#
b101 *
b101 /#
#110000
b1 $
b1 1#
b11 2#
b1110 #
b1110 0#
1'
b1001 )
b1001 .#
b1101 *
b1101 /#
#111000
b0 $
b0 1#
b1 2#
b1101 #
b1101 0#
0'
b1100 )
b1100 .#
b1100 *
b1100 /#
#112000
b1111 $
b1111 1#
b11111 2#
b1010 #
b1010 0#
1'
b1011 )
b1011 .#
b101 *
b101 /#
#113000
b1011 $
b1011 1#
b10111 2#
b110 #
b110 0#
b1 *
b1 /#
#114000
b0 $
b0 1#
b1111 #
b1111 0#
b0 2#
0(
0'
b1010 )
b1010 .#
b1111 *
b1111 /#
#115000
b1011 $
b1011 1#
b100 #
b100 0#
b10111 2#
1(
1'
b1011 )
b1011 .#
b11 *
b11 /#
#116000
b0 $
b0 1#
b1101 #
b1101 0#
b0 2#
0(
0'
b1000 )
b1000 .#
b1101 *
b1101 /#
