build/gemdiff/xilinx_macros_ref.v
// ===========================================================================
// CROSS-CHECK AGAINST PUBLIC XILINX FUNCTIONAL DOCUMENTATION
// ===========================================================================
// These are clean-room models written from documented functional behaviour.
// No UNISIM source was consulted or copied; UNISIM is proprietary and is not
// present in this environment.
//
// Document mapping (CONFIRMED):
//   UG579 - UltraScale Architecture DSP Slice User Guide  -> DSP48E2   <== ours
//   UG479 - 7 Series DSP48E1 Slice User Guide             -> DSP48E1  (NOT ours)
//   UG474 - 7 Series FPGAs Configurable Logic Block Guide -> CARRY4, SRLC32E
//
// The problem statement targets DSP48E2, so UG579 is the applicable DSP guide.
// UG479 covers the older DSP48E1 and does NOT describe our target part.
//
// ---------------------------------------------------------------------------
// DSP48E2: deviations of THIS MODEL from full silicon, all spec-mandated
// ---------------------------------------------------------------------------
// Matches documented DSP48E2 behaviour:
//   - 27x18 signed multiplier producing a 45-bit product
//   - 48-bit P accumulator register
//   - 27-bit pre-adder whose sum wraps at 27 bits
//   - D port 27 bits, B port 18 bits, C port 48 bits
//
// Deliberate simplifications imposed by the problem statement:
//   1. A PORT WIDTH. Real DSP48E2 has a 30-bit A port (A[29:0]); only the low
//      27 bits reach the pre-adder, while the full width feeds the A:B
//      concatenation path. The problem statement fixes A at 27 bits, so this
//      model uses 27. Anything relying on A[29:27] is out of scope.
//   2. PRE-ADDER. Real silicon computes D +/- A under INMODE control. The
//      statement fixes AD = A + D (addition only), or A passed through.
//   3. OPMODE/ALUMODE. Real silicon selects the datapath with a 9-bit OPMODE
//      plus a 4-bit ALUMODE. The statement replaces both with a 2-bit state:
//      0 = P<=C, 1 = P<=M, 2 = P<=P+M.
//   4. PIPELINE REGISTERS. AREG=BREG=CREG=DREG=ADREG=MREG=0, PREG=1.
//   5. NOT MODELLED: PCIN/PCOUT cascade, CARRYIN/CARRYCASCIN/CARRYOUT,
//      pattern detector, SIMD modes, wide XOR, and the OVERFLOW/UNDERFLOW
//      pins (the statement explicitly puts OVERFLOW/UNDERFLOW out of scope).
//
// ---------------------------------------------------------------------------
// CARRY4: agrees with UG474 with no simplification
// ---------------------------------------------------------------------------
//   UG474 describes the carry chain as, per bit i:
//       O[i]  = S[i] XOR C[i]
//       C[i+1] = S[i] ? C[i] : DI[i]
//   The mux form S ? C : DI is Boolean-identical to the form used here,
//   (S & C) | (~S & DI), so the two descriptions agree exactly.
//   CYINIT initialises the bottom CARRY4 of a chain; CIN carries the cascade
//   into every later block. Exactly one is active in valid RTL, which is why
//   C[0] = CYINIT | CIN is a faithful encoding rather than a shortcut.
//
// ---------------------------------------------------------------------------
// SRLC32E: agrees with UG474 apart from INIT
// ---------------------------------------------------------------------------
//   32-bit shift register, CE-gated, shifting on the rising clock edge;
//   Q reads the bit selected by the 5-bit address A; Q31 is the fixed bit-31
//   cascade output used to chain SRLs together.
//   Deviation: the real primitive takes an INIT parameter for initial
//   contents. The problem statement puts INIT parsing out of scope, so the
//   register always starts at zero here.
// ===========================================================================

// SPDX-License-Identifier: Apache-2.0
// Behavioural golden models for the three Xilinx primitives GEM must
// evaluate natively.
//
// These are written to be as LITERAL a transcription of the problem
// statement's equations as possible -- in particular CARRY4_ref is a genuine
// four-step ripple, and carry_chain_ref really does daisy-chain CO[3] into
// the next block's CI. They are intentionally NOT clever.
//
// The point of that is independence: csrc/gem_macros.cuh evaluates a fused
// carry chain as a single 64-bit add, and the whole verification argument is
// that the clever version and this literal version agree on random vectors.
// If both files shared an optimisation, the test would prove nothing.

`timescale 1ns / 1ps

// ---------------------------------------------------------------------------
// CARRY4 -- literal transcription of the silicon equations
// ---------------------------------------------------------------------------
//   C[0]   = CYINIT | CI
//   C[i+1] = (S[i] & C[i]) | (~S[i] & DI[i])
//   O[i]   = S[i] ^ C[i]
//   CO[i]  = C[i+1]
module CARRY4_ref (
    output [3:0] CO,
    output [3:0] O,
    input        CI,
    input        CYINIT,
    input  [3:0] DI,
    input  [3:0] S
);
    wire [4:0] C;
    assign C[0] = CYINIT | CI;

    genvar i;
    generate
        for (i = 0; i < 4; i = i + 1) begin : gen_bit
            assign C[i+1] = (S[i] & C[i]) | (~S[i] & DI[i]);
            assign O[i]   = S[i] ^ C[i];
            assign CO[i]  = C[i+1];
        end
    endgenerate
endmodule

// ---------------------------------------------------------------------------
// A cascade of NBLK CARRY4s, wired CO[3] -> CI exactly as a synthesiser would
// emit for a wide adder. This is the structure GEM must recognise and fuse.
// ---------------------------------------------------------------------------
module carry_chain_ref #(
    parameter NBLK = 15
) (
    output [4*NBLK-1:0] O,
    output [4*NBLK-1:0] CO,
    input               CYINIT,
    input  [4*NBLK-1:0] DI,
    input  [4*NBLK-1:0] S
);
    wire [NBLK:0] cc;
    assign cc[0] = 1'b0;

    genvar b;
    generate
        for (b = 0; b < NBLK; b = b + 1) begin : gen_blk
            CARRY4_ref u_c4 (
                .CO     (CO[4*b+3 -: 4]),
                .O      (O [4*b+3 -: 4]),
                // Block 0 takes the chain initialiser on CYINIT; every later
                // block takes the previous block's CO[3] on CI. Only one of
                // the two is ever active, per the problem statement.
                .CI     ((b == 0) ? 1'b0   : cc[b]),
                .CYINIT ((b == 0) ? CYINIT : 1'b0),
                .DI     (DI[4*b+3 -: 4]),
                .S      (S [4*b+3 -: 4])
            );
            assign cc[b+1] = CO[4*b+3];
        end
    endgenerate
endmodule

// ---------------------------------------------------------------------------
// DSP48E2 simplified subset
// ---------------------------------------------------------------------------
// AREG/BREG/CREG/DREG/ADREG/MREG = 0 (combinational), PREG = 1 (clocked).
//   AD     = use_pre ? A + D : A      (wraps at 27 bits)
//   M      = AD * B                   (45-bit signed)
//   P_next = state==0 ? C : state==1 ? M : P + M
module dsp48e2_ref (
    output reg signed [47:0] P,
    input                    clk,
    input      signed [26:0] A,
    input      signed [26:0] D,
    input      signed [17:0] B,
    input      signed [47:0] C,
    input             [1:0]  state,
    input                    use_pre
);
    // 27-bit pre-adder: the sum truncates back to 27 bits.
    wire signed [26:0] AD = use_pre ? (A + D) : A;
    // 27 x 18 -> 45 bit signed product.
    wire signed [44:0] M  = AD * B;

    reg signed [47:0] p_next;
    always @(*) begin
        case (state)
            2'd0:    p_next = C;        // bypass
            2'd1:    p_next = M;        // multiply only
            default: p_next = P + M;    // multiply-accumulate
        endcase
    end

    initial P = 48'd0;                  // registers initialise to zero
    always @(posedge clk) P <= p_next;
endmodule

// ---------------------------------------------------------------------------
// SRLC32E shift register LUT
// ---------------------------------------------------------------------------
//   on posedge, if CE: state <= {state[30:0], D}   (shift LSB -> MSB)
//   Q   = state[A]    combinational, dynamic address
//   Q31 = state[31]   combinational cascade output
module srlc32e_ref (
    output       Q,
    output       Q31,
    input        clk,
    input        CE,
    input        D,
    input  [4:0] A
);
    reg [31:0] state;
    initial state = 32'd0;              // registers initialise to zero

    assign Q   = state[A];
    assign Q31 = state[31];

    always @(posedge clk) begin
        if (CE) state <= {state[30:0], D};
    end
endmodule

build/gemdiff/tb_dsp48e2.v
// Differential testbench: DSP48E2 simplified subset (PREG=1, all else comb).
// One stimulus line per clock cycle; records the P register AFTER each edge.
`timescale 1ns/1ps
`include "xilinx_macros_ref.v"

module tb_dsp48e2;
    reg                clk;
    reg  signed [26:0] A, D;
    reg  signed [17:0] B;
    reg  signed [47:0] C;
    reg         [1:0]  state;
    reg                use_pre;
    wire signed [47:0] P;

    dsp48e2_ref u_dsp (.P(P), .clk(clk), .A(A), .D(D), .B(B), .C(C),
                       .state(state), .use_pre(use_pre));

    integer fi, fo, n;

    // Waveform capture for inspection. Written under sim_out/,
    // never the repo root.
    initial begin
        $dumpfile("sim_out/tb_dsp48e2.vcd");
        $dumpvars(0, tb_dsp48e2);
    end

    initial begin
        clk = 1'b0;
        fi = $fopen("sim_out/stim_dsp.txt", "r");
        fo = $fopen("sim_out/res_dsp.txt", "w");
        if (fi == 0 || fo == 0) begin $display("FILE ERROR"); $finish; end

        n = $fscanf(fi, "%h %h %h %h %h %h\n", A, D, B, C, state, use_pre);
        while (n == 6) begin
            #1;                 // let the combinational cone settle
            clk = 1'b1; #1;     // rising edge: P latches
            clk = 1'b0; #1;
            $fdisplay(fo, "%h", P);
            n = $fscanf(fi, "%h %h %h %h %h %h\n", A, D, B, C, state, use_pre);
        end
        $fclose(fi); $fclose(fo);
        $finish;
    end
endmodule

build/gemdiff/sim_out/tb_dsp48e2.vcd
$date
	Wed Aug 26 20:51:46 2026
$end
$version
	Icarus Verilog
$end
$timescale
	1ps
$end
$scope module tb_dsp48e2 $end
$var wire 48 ! P [47:0] $end
$var reg 27 " A [26:0] $end
$var reg 18 # B [17:0] $end
$var reg 48 $ C [47:0] $end
$var reg 27 % D [26:0] $end
$var reg 1 & clk $end
$var reg 2 ' state [1:0] $end
$var reg 1 ( use_pre $end
$var integer 32 ) fi [31:0] $end
$var integer 32 * fo [31:0] $end
$var integer 32 + n [31:0] $end
$scope module u_dsp $end
$var wire 27 , A [26:0] $end
$var wire 18 - B [17:0] $end
$var wire 48 . C [47:0] $end
$var wire 27 / D [26:0] $end
$var wire 1 & clk $end
$var wire 2 0 state [1:0] $end
$var wire 1 ( use_pre $end
$var wire 45 1 M [44:0] $end
$var wire 27 2 AD [26:0] $end
$var reg 48 3 P [47:0] $end
$var reg 48 4 p_next [47:0] $end
$upscope $end
$upscope $end
$enddefinitions $end
$comment Show the parameter values. $end
$dumpall
$end
#0
$dumpvars
b0 4
b0 3
b0 2
b0 1
b0 0
b0 /
b0 .
b0 -
b0 ,
b110 +
b10000000000000000000000000000100 *
b10000000000000000000000000000011 )
0(
b0 '
0&
b0 %
b0 $
b0 #
b0 "
b0 !
$end
#1000
1&
#2000
0&
#3000
b111111111111111111111111111111111111111111111111 4
b1 1
b111111111111111111111111111 2
b111111111111111111111111111111111111111111111111 $
b111111111111111111111111111111111111111111111111 .
b111111111111111111 #
b111111111111111111 -
b111111111111111111111111111 %
b111111111111111111111111111 /
b111111111111111111111111111 "
b111111111111111111111111111 ,
#4000
b111111111111111111111111111111111111111111111111 !
b111111111111111111111111111111111111111111111111 3
1&
#5000
0&
#6000
b0 4
b100000000000000000000000000 2
b0 $
b0 .
b10000000000000000000000000000000000000000000 1
b100000000000000000 #
b100000000000000000 -
b100000000000000000000000000 %
b100000000000000000000000000 /
b100000000000000000000000000 "
b100000000000000000000000000 ,
#7000
b0 !
b0 3
1&
#8000
0&
#9000
b11111111111111111111111111 2
b1111111111111111011111111100000000000000001 1
b11111111111111111 #
b11111111111111111 -
b0 %
b0 /
b11111111111111111111111111 "
b11111111111111111111111111 ,
#10000
1&
#11000
0&
#12000
b111111111111111111111111111111111111111111111111 4
b100000000000000000000000000 2
b111111111111111111111111111111111111111111111111 $
b111111111111111111111111111111111111111111111111 .
b10000000000000000000000000000000000000000000 1
b100000000000000000 #
b100000000000000000 -
b1 %
b1 /
b100000000000000000000000000 "
b100000000000000000000000000 ,
#13000
b111111111111111111111111111111111111111111111111 !
b111111111111111111111111111111111111111111111111 3
1&
#14000
0&
#15000
b0 4
b1 2
b0 $
b0 .
b1 1
b1 #
b1 -
b111111111111111111111111111 %
b111111111111111111111111111 /
b1 "
b1 ,
#16000
b0 !
b0 3
1&
#17000
0&
#18000
b0 2
1(
b0 1
b0 #
b0 -
b0 %
b0 /
b0 "
b0 ,
#19000
1&
#20000
0&
#21000
b111111111111111111111111111111111111111111111111 4
b10 1
b111111111111111111111111110 2
b111111111111111111111111111111111111111111111111 $
b111111111111111111111111111111111111111111111111 .
b111111111111111111 #
b111111111111111111 -
b111111111111111111111111111 %
b111111111111111111111111111 /
b111111111111111111111111111 "
b111111111111111111111111111 ,
#22000
b111111111111111111111111111111111111111111111111 !
b111111111111111111111111111111111111111111111111 3
1&
#23000
0&
#24000
b0 4
b0 2
b0 $
b0 .
b0 1
b100000000000000000 #
b100000000000000000 -
b100000000000000000000000000 %
b100000000000000000000000000 /
b100000000000000000000000000 "
b100000000000000000000000000 ,
#25000
b0 !
b0 3
1&
#26000
0&
#27000
b1111111111111111011111111100000000000000001 1
b11111111111111111111111111 2
b11111111111111111 #
b11111111111111111 -
b0 %
b0 /
b11111111111111111111111111 "
b11111111111111111111111111 ,
#28000
1&
#29000
0&
#30000
b111111111111111111111111111111111111111111111111 4
b100000000000000000000000001 2
b111111111111111111111111111111111111111111111111 $
b111111111111111111111111111111111111111111111111 .
b1111111111111111111111111100000000000000000 1
b100000000000000000 #
b100000000000000000 -
b1 %
b1 /
b100000000000000000000000000 "
b100000000000000000000000000 ,
#31000
b111111111111111111111111111111111111111111111111 !
b111111111111111111111111111111111111111111111111 3
1&
#32000
0&
#33000
b0 4
b0 2
b0 $
b0 .
b0 1
b1 #
b1 -
b111111111111111111111111111 %
b111111111111111111111111111 /
b1 "
b1 ,
#34000
b0 !
b0 3
1&
#35000
0&
#36000
0(
b1 '
b1 0
b0 #
b0 -
b0 %
b0 /
b0 "
b0 ,
#37000
1&
#38000
0&
#39000
b1 4
b1 1
b111111111111111111111111111 2
b111111111111111111111111111111111111111111111111 $
b111111111111111111111111111111111111111111111111 .
b111111111111111111 #
b111111111111111111 -
b111111111111111111111111111 %
b111111111111111111111111111 /
b111111111111111111111111111 "
b111111111111111111111111111 ,
#40000
b1 !
b1 3
1&
#41000
0&
#42000
b10000000000000000000000000000000000000000000 4
b100000000000000000000000000 2
b0 $
b0 .
b10000000000000000000000000000000000000000000 1
b100000000000000000 #
b100000000000000000 -
b100000000000000000000000000 %
b100000000000000000000000000 /
b100000000000000000000000000 "
b100000000000000000000000000 ,
#43000
b10000000000000000000000000000000000000000000 !
b10000000000000000000000000000000000000000000 3
1&
#44000
0&
#45000
b1111111111111111011111111100000000000000001 4
b11111111111111111111111111 2
b1111111111111111011111111100000000000000001 1
b11111111111111111 #
b11111111111111111 -
b0 %
b0 /
b11111111111111111111111111 "
b11111111111111111111111111 ,
#46000
b1111111111111111011111111100000000000000001 !
b1111111111111111011111111100000000000000001 3
1&
#47000
0&
#48000
b10000000000000000000000000000000000000000000 4
b100000000000000000000000000 2
b111111111111111111111111111111111111111111111111 $
b111111111111111111111111111111111111111111111111 .
b10000000000000000000000000000000000000000000 1
b100000000000000000 #
b100000000000000000 -
b1 %
b1 /
b100000000000000000000000000 "
b100000000000000000000000000 ,
#49000
b10000000000000000000000000000000000000000000 !
b10000000000000000000000000000000000000000000 3
1&
#50000
0&
#51000
b1 4
b1 2
b0 $
b0 .
b1 1
b1 #
b1 -
b111111111111111111111111111 %
b111111111111111111111111111 /
b1 "
b1 ,
#52000
b1 !
b1 3
1&
#53000
0&
#54000
b0 4
b0 2
1(
b0 1
b0 #
b0 -
b0 %
b0 /
b0 "
b0 ,
#55000
b0 !
b0 3
1&
#56000
0&
#57000
b10 4
b10 1
b111111111111111111111111110 2
b111111111111111111111111111111111111111111111111 $
b111111111111111111111111111111111111111111111111 .
b111111111111111111 #
b111111111111111111 -
b111111111111111111111111111 %
b111111111111111111111111111 /
b111111111111111111111111111 "
b111111111111111111111111111 ,
#58000
b10 !
b10 3
1&
#59000
0&
#60000
b0 4
b0 2
b0 $
b0 .
b0 1
b100000000000000000 #
b100000000000000000 -
b100000000000000000000000000 %
b100000000000000000000000000 /
b100000000000000000000000000 "
b100000000000000000000000000 ,
#61000
b0 !
b0 3
1&
#62000
0&
#63000
b1111111111111111011111111100000000000000001 4
b1111111111111111011111111100000000000000001 1
b11111111111111111111111111 2
b11111111111111111 #
b11111111111111111 -
b0 %
b0 /
b11111111111111111111111111 "
b11111111111111111111111111 ,
#64000
b1111111111111111011111111100000000000000001 !
b1111111111111111011111111100000000000000001 3
1&
#65000
0&
#66000
b1111111111111111111111111100000000000000000 4
b100000000000000000000000001 2
b111111111111111111111111111111111111111111111111 $
b111111111111111111111111111111111111111111111111 .
b1111111111111111111111111100000000000000000 1
b100000000000000000 #
b100000000000000000 -
b1 %
b1 /
b100000000000000000000000000 "
b100000000000000000000000000 ,
#67000
b1111111111111111111111111100000000000000000 !
b1111111111111111111111111100000000000000000 3
1&
#68000
0&
#69000
b0 4
b0 2
b0 $
b0 .
b0 1
b1 #
b1 -
b111111111111111111111111111 %
b111111111111111111111111111 /
b1 "
b1 ,
#70000
b0 !
b0 3
1&
#71000
0&
#72000
0(
b10 '
b10 0
b0 #
b0 -
b0 %
b0 /
b0 "
b0 ,
#73000
1&
#74000
0&
#75000
b1 4
b1 1
b111111111111111111111111111 2
b111111111111111111111111111111111111111111111111 $
b111111111111111111111111111111111111111111111111 .
b111111111111111111 #
b111111111111111111 -
b111111111111111111111111111 %
b111111111111111111111111111 /
b111111111111111111111111111 "
b111111111111111111111111111 ,
#76000
b10 4
b1 !
b1 3
1&
#77000
0&
#78000
b10000000000000000000000000000000000000000001 4
b100000000000000000000000000 2
b0 $
b0 .
b10000000000000000000000000000000000000000000 1
b100000000000000000 #
b100000000000000000 -
b100000000000000000000000000 %
b100000000000000000000000000 /
b100000000000000000000000000 "
b100000000000000000000000000 ,
#79000
b100000000000000000000000000000000000000000001 4
b10000000000000000000000000000000000000000001 !
b10000000000000000000000000000000000000000001 3
1&
#80000
0&
#81000
b11111111111111111011111111100000000000000010 4
b11111111111111111111111111 2
b1111111111111111011111111100000000000000001 1
b11111111111111111 #
b11111111111111111 -
b0 %
b0 /
b11111111111111111111111111 "
b11111111111111111111111111 ,
#82000
b101111111111111110111111111000000000000000011 4
b11111111111111111011111111100000000000000010 !
b11111111111111111011111111100000000000000010 3
1&
#83000
0&
#84000
b101111111111111111011111111100000000000000010 4
b100000000000000000000000000 2
b111111111111111111111111111111111111111111111111 $
b111111111111111111111111111111111111111111111111 .
b10000000000000000000000000000000000000000000 1
b100000000000000000 #
b100000000000000000 -
b1 %
b1 /
b100000000000000000000000000 "
b100000000000000000000000000 ,
#85000
b111111111111111111011111111100000000000000010 4
b101111111111111111011111111100000000000000010 !
b101111111111111111011111111100000000000000010 3
1&
#86000
0&
#87000
b101111111111111111011111111100000000000000011 4
b1 2
b0 $
b0 .
b1 1
b1 #
b1 -
b111111111111111111111111111 %
b111111111111111111111111111 /
b1 "
b1 ,
#88000
b101111111111111111011111111100000000000000100 4
b101111111111111111011111111100000000000000011 !
b101111111111111111011111111100000000000000011 3
1&
#89000
0&
#90000
b101111111111111111011111111100000000000000011 4
b0 2
1(
b0 1
b0 #
b0 -
b0 %
b0 /
b0 "
b0 ,
#91000
1&
#92000
0&
#93000
b101111111111111111011111111100000000000000101 4
b10 1
b111111111111111111111111110 2
b111111111111111111111111111111111111111111111111 $
b111111111111111111111111111111111111111111111111 .
b111111111111111111 #
b111111111111111111 -
b111111111111111111111111111 %
b111111111111111111111111111 /
b111111111111111111111111111 "
b111111111111111111111111111 ,
#94000
b101111111111111111011111111100000000000000111 4
b101111111111111111011111111100000000000000101 !
b101111111111111111011111111100000000000000101 3
1&
#95000
0&
#96000
b101111111111111111011111111100000000000000101 4
b0 2
b0 $
b0 .
b0 1
b100000000000000000 #
b100000000000000000 -
b100000000000000000000000000 %
b100000000000000000000000000 /
b100000000000000000000000000 "
b100000000000000000000000000 ,
#97000
1&
#98000
0&
#99000
b111111111111111110111111111000000000000000110 4
b1111111111111111011111111100000000000000001 1
b11111111111111111111111111 2
b11111111111111111 #
b11111111111111111 -
b0 %
b0 /
b11111111111111111111111111 "
b11111111111111111111111111 ,
#100000
b1001111111111111110011111110100000000000000111 4
b111111111111111110111111111000000000000000110 !
b111111111111111110111111111000000000000000110 3
1&
#101000
0&
#102000
b1001111111111111110111111110100000000000000110 4
b100000000000000000000000001 2
b111111111111111111111111111111111111111111111111 $
b111111111111111111111111111111111111111111111111 .
b1111111111111111111111111100000000000000000 1
b100000000000000000 #
b100000000000000000 -
b1 %
b1 /
b100000000000000000000000000 "
b100000000000000000000000000 ,
#103000
b1011111111111111110111111110000000000000000110 4
b1001111111111111110111111110100000000000000110 !
b1001111111111111110111111110100000000000000110 3
1&
#104000
0&
#105000
b1001111111111111110111111110100000000000000110 4
b0 2
b0 $
b0 .
b0 1
b1 #
b1 -
b111111111111111111111111111 %
b111111111111111111111111111 /
b1 "
b1 ,
#106000
1&
#107000
0&
#108000
b1001100001111111000011000111010111100010001011 4
b111100001111111001011001000110111100010000101 1
b111100011110100111110001 2
b11101110110110001101110101001110111001001110100 $
b11101110110110001101110101001110111001001110100 .
b100000001111010101 #
b100000001111010101 -
b11011100110011010010010000 %
b11011100110011010010010000 /
b101011111101011010101100001 "
b101011111101011010101100001 ,
#109000
b1001000011111110001110010000001111000100010000 4
b1001100001111111000011000111010111100010001011 !
b1001100001111111000011000111010111100010001011 3
1&
#110000
0&
#111000
b1001110110110101010101110010010000001001011111 4
b101110010111010100111001 2
b110000001001101101011110001010010111011001111011 $
b110000001001101101011110001010010111011001111011 .
b10100110110010010101010111000100111010100 1
b11100110001110100 #
b11100110001110100 -
b110001110110000001111101100 %
b110001110110000001111101100 /
b10011111100111000101001101 "
b10011111100111000101001101 ,
#112000
b1010001011101011101000011101001000110000110011 4
b1001110110110101010101110010010000001001011111 !
b1001110110110101010101110010010000001001011111 3
1&
#113000
0&
#114000
b1001100111101000101110100101010110110101001101 4
b100111000100010000111110 2
b11000010010000100010010100011011110010100010010 $
b11000010010000100010010100011011110010100010010 .
b111110000110011011000110011000110101011101110 1
b100111000110101001 #
b100111000110101001 -
b110111011100000100100101010 %
b110111011100000100100101010 /
b1101011100011101100010100 "
b1101011100011101100010100 ,
#115000
b1001011000011100000111011000011101100000111011 4
b1001100111101000101110100101010110110101001101 !
b1001100111101000101110100101010110110101001101 3
1&
#116000
0&
#117000
b1010111110011110111001010111000100110001110110 4
b11111000010100100000001001 2
b111111011101010011100100001000111000011111101010 $
b111111011101010011100100001000111000011111101010 .
b1010110110110001010110001101101111100101001 1
b10110011000100001 #
b10110011000100001 -
b11101101100111101011101111 %
b11101101100111101011101111 /
b1010101100110100011010 "
b1010101100110100011010 ,
#118000
b1100010101010101000100001000110010101110011111 4
b1010111110011110111001010111000100110001110110 !
b1010111110011110111001010111000100110001110110 3
1&
#119000
0&
#120000
b1010011110111111101000001101111000111011010011 4
b1111010000100000011101011 2
b110110011110011111010001100000010000011100100110 $
b110110011110011111010001100000010000011100100110 .
b111100000100000101110110110110100001001011101 1
b101111011111010111 #
b101111011111010111 -
b111101100001101010100000 %
b111101100001101010100000 /
b111100100010011001001011 "
b111100100010011001001011 ,
#121000
b1001111111100000010111000100101101000100110000 4
b1010011110111111101000001101111000111011010011 !
b1010011110111111101000001101111000111011010011 3
1&
#122000
0&
#123000
b1011001100111110000111011010110001101011010011 4
b101011010001110011101111011 2
b1011010110101001011111001101101010010000010110 $
b1011010110101001011111001101101010010000010110 .
b101101111110011111001100111000110000000000 1
b101110010000000000 #
b101110010000000000 -
b1101001101000110110110011 %
b1101001101000110110110011 /
b11110000100101100111001000 "
b11110000100101100111001000 ,
#124000
b1011111010111100100110100111101010011011010011 4
b1011001100111110000111011010110001101011010011 !
b1011001100111110000111011010110001101011010011 3
1&
#125000
0&
#126000
b1011111110111001000111000010000101010100001010 4
b101010100101000110111111001 2
b110111011011000011011010101000001110100001111000 $
b110111011011000011011010101000001110100001111000 .
b110001111010111111100111010011101000110111 1
b101101010110101111 #
b101101010110101111 -
b101000110011011010010110110 %
b101000110011011010010110110 /
b1110001101100101000011 "
b1110001101100101000011 ,
#127000
b1100110000110100000110101001011000111101000001 4
b1011111110111001000111000010000101010100001010 !
b1011111110111001000111000010000101010100001010 3
1&
#128000
0&
#129000
b1101000000000000000001110111110100101010101001 4
b100000100011001001101010011 2
b101001010010110010100100001001001111001101011011 $
b101001010010110010100100001001001111001101011011 .
b1000001000110111010110101101111010110011111 1
b101111011100000101 #
b101111011100000101 -
b11101001100001000111011100 %
b11101001100001000111011100 /
b11010111000000101110111 "
b11010111000000101110111 ,
#130000
b1110000001000110111100101101100100000001001000 4
b1101000000000000000001110111110100101010101001 !
b1101000000000000000001110111110100101010101001 3
1&
#131000
0&
#132000
b1100011101000000110100101111110000111010101010 4
b11010100000111100100101001 2
b110011011100000011001001101100010110110110000 $
b110011011100000011001001101100010110110110000 .
b111011101000000110010110111111100010000000001 1
b110101011100011001 #
b110101011100011001 -
b110011000011001000000111111 %
b110011000011001000000111111 /
b100111011101110100011101010 "
b100111011101110100011101010 ,
#133000
b1011111010000001100111100111101101001010101011 4
b1100011101000000110100101111110000111010101010 !
b1100011101000000110100101111110000111010101010 3
1&
#134000
0&
#135000
b1100011110111000000011111011001000000001000010 4
b100100111111011100001 2
b110101000101000101110000101101000001101011100111 $
b110101000101000101110000101101000001101011100111 .
b1110111001111001011010111000110011000 1
b11001110010011000 #
b11001110010011000 -
b1011011010100110011011010 %
b1011011010100110011011010 /
b110101001010011001000000111 "
b110101001010011001000000111 ,
#136000
b1100100000101111010011000110011111000111011010 4
b1100011110111000000011111011001000000001000010 !
b1100011110111000000011111011001000000001000010 3
1&
#137000
0&
#138000
b1100100010001100001110011010101000101111110001 4
b110111101110010011110011101 2
b10001111011011001111001001010100010000100010010 $
b10001111011011001111001001010100010000100010010 .
b11010100001010011111100000101110101111 1
b111100110010111011 #
b111100110010111011 -
b110001110001011001000001111 %
b110001110001011001000001111 /
b101111100111010110001110 "
b101111100111010110001110 ,
#139000
b1100100101100000011000111010001001011110100000 4
b1100100010001100001110011010101000101111110001 !
b1100100010001100001110011010101000101111110001 3
1&
#140000
0&
#141000
b1011111000011100100101010010010111100110001001 4
b101100111001101001111000110 2
b100011011010101011010110011100000001010010100011 $
b100011011010101011010110011100000001010010100011 .
b111010110010000010110110111101110110110011000 1
b10001011111000100 #
b10001011111000100 -
b1010100001101010110111010 %
b1010100001101010110111010 /
b100010010111111111000001100 "
b100010010111111111000001100 ,
#142000
b1011001110101100111100001010000110011100100001 4
b1011111000011100100101010010010111100110001001 !
b1011111000011100100101010010010111100110001001 3
1&
#143000
0&
#144000
b1101010010110100111001000101100010110110101001 4
b100010100010010000001010011 2
b100111010100000001001101011101011110001111011110 $
b100111010100000001001101011101011110001111011110 .
b1011010011000010011110011001011010000100000 1
b100111011101100000 #
b100111011101100000 -
b11001101111110001001011 %
b11001101111110001001011 /
b11111010100010010000001000 "
b11111010100010010000001000 ,
#145000
b1110101101001101001100111000101110000111001001 4
b1101010010110100111001000101100010110110101001 !
b1101010010110100111001000101100010110110101001 3
1&
#146000
0&
#147000
b1101010101111011010100110000010101111110111001 4
b10011010000111000100101000 2
b10010001101010011101011001000100111011000001010 $
b10010001101010011101011001000100111011000001010 .
b11000110011011101010110011001000010000 1
b1010010011010 #
b1010010011010 -
b11001111111000110100111010 %
b11001111111000110100111010 /
b111001010001110001111101110 "
b111001010001110001111101110 ,
#148000
b1101011001000001110000011011001001000111001001 4
b1101010101111011010100110000010101111110111001 !
b1101010101111011010100110000010101111110111001 3
1&
#149000
0&
#150000
b1101011001000000000100010100001111100010011001 4
b111110100010101011001101100 2
b11110111011001100110011010101000101010010101110 $
b11110111011001100110011010101000101010010101110 .
b11000100101111100011111001100011100000 1
b101111001000101000 #
b101111001000101000 -
b1101001101010011000011110 %
b1101001101010011000011110 /
b110001010101011000001001110 "
b110001010101011000001001110 ,
#151000
b1101011100000100110011111000001001000101111001 4
b1101011001000000000100010100001111100010011001 !
b1101011001000000000100010100001111100010011001 3
1&
#152000
0&
#153000
b1101011010110101000010101011100110000011111101 4
b101110101111011110101 2
b101100100111100011100111111111011000101110010011 $
b101100100111100011100111111111011000101110010011 .
b1110100111110010111010110100001100100 1
b10100000001010100 #
b10100000001010100 -
b111010010100110101100111001 %
b111010010100110101100111001 /
b110011001111001110111100 "
b110011001111001110111100 ,
#154000
b1101011100101010000001000010111100100101100001 4
b1101011010110101000010101011100110000011111101 !
b1101011010110101000010101011100110000011111101 3
1&
#155000
0&
#156000
b1101010110001111010110111001101101001010000101 4
b100110001100110000100000010 2
b10111001100011000111000001001100100011000011110 $
b10111001100011000111000001001100100011000011110 .
b111111011011010010100001110000111000110001000 1
b1011011000100 #
b1011011000100 -
b100011010001100011110111100 %
b100011010001100011110111100 /
b10111011001100101000110 "
b10111011001100101000110 ,
#157000
b1101010001101001101011000111110100010000001101 4
b1101010110001111010110111001101101001010000101 !
b1101010110001111010110111001101101001010000101 3
1&
#158000
0&
#159000
b1100001110011000100001110001011001101110000110 4
b10100010010111001100101111 2
b10101010100011000000111001011001001100100010100 $
b10101010100011000000111001011001001100100010100 .
b110111000001001001010110111101100100100000001 1
b100011101011001111 #
b100011101011001111 -
b11100100010010000010110001 %
b11100100010010000010110001 /
b110111110000101001001111110 "
b110111110000101001001111110 ,
#160000
b1011000110100001101100101001000110010010000111 4
b1100001110011000100001110001011001101110000110 !
b1100001110011000100001110001011001101110000110 3
1&
#161000
0&
#162000
b1100000110000110111001111000011111111000110000 4
b110100011010110100100100110 2
b1100101101011110111101100011111101100011100011 $
b1100101101011110111101100011111101100011100011 .
b111110111101110011000000111000110001010101010 1
b101101101110111 #
b101101101110111 -
b10001101011111110111100001 %
b10001101011111110111100001 /
b100010101110110101101000101 "
b100010101110110101101000101 ,
#163000
b1011111101110101010001111111100110000011011010 4
b1100000110000110111001111000011111111000110000 !
b1100000110000110111001111000011111111000110000 3
1&
#164000
0&
#165000
b1011010111010111111110011000101110000110111000 4
b10011011111011110100001110 2
b110100011000000100000011111101000010111011110110 $
b110100011000000100000011111101000010111011110110 .
b111010001010001000100100000001110001110001000 1
b101100110100011100 #
b101100110100011100 -
b11011011001001011100011 %
b11011011001001011100011 /
b10000000100010101000101011 "
b10000000100010101000101011 ,
#166000
b1010101000101001000010111000111100010101000000 4
b1011010111010111111110011000101110000110111000 !
b1011010111010111111110011000101110000110111000 3
1&
#167000
0&
