build/gemdiff/xilinx_macros_ref.v
// ===========================================================================
// CROSS-CHECK AGAINST PUBLIC XILINX FUNCTIONAL DOCUMENTATION
// ===========================================================================
// These are clean-room models written from documented functional behaviour.
// No UNISIM source was consulted or copied; UNISIM is proprietary and is not
// present in this environment.
//
// Document mapping (CONFIRMED):
//   UG579 - UltraScale Architecture DSP Slice User Guide  -> DSP48E2   <== ours
//   UG479 - 7 Series DSP48E1 Slice User Guide             -> DSP48E1  (NOT ours)
//   UG474 - 7 Series FPGAs Configurable Logic Block Guide -> CARRY4, SRLC32E
//
// The problem statement targets DSP48E2, so UG579 is the applicable DSP guide.
// UG479 covers the older DSP48E1 and does NOT describe our target part.
//
// ---------------------------------------------------------------------------
// DSP48E2: deviations of THIS MODEL from full silicon, all spec-mandated
// ---------------------------------------------------------------------------
// Matches documented DSP48E2 behaviour:
//   - 27x18 signed multiplier producing a 45-bit product
//   - 48-bit P accumulator register
//   - 27-bit pre-adder whose sum wraps at 27 bits
//   - D port 27 bits, B port 18 bits, C port 48 bits
//
// Deliberate simplifications imposed by the problem statement:
//   1. A PORT WIDTH. Real DSP48E2 has a 30-bit A port (A[29:0]); only the low
//      27 bits reach the pre-adder, while the full width feeds the A:B
//      concatenation path. The problem statement fixes A at 27 bits, so this
//      model uses 27. Anything relying on A[29:27] is out of scope.
//   2. PRE-ADDER. Real silicon computes D +/- A under INMODE control. The
//      statement fixes AD = A + D (addition only), or A passed through.
//   3. OPMODE/ALUMODE. Real silicon selects the datapath with a 9-bit OPMODE
//      plus a 4-bit ALUMODE. The statement replaces both with a 2-bit state:
//      0 = P<=C, 1 = P<=M, 2 = P<=P+M.
//   4. PIPELINE REGISTERS. AREG=BREG=CREG=DREG=ADREG=MREG=0, PREG=1.
//   5. NOT MODELLED: PCIN/PCOUT cascade, CARRYIN/CARRYCASCIN/CARRYOUT,
//      pattern detector, SIMD modes, wide XOR, and the OVERFLOW/UNDERFLOW
//      pins (the statement explicitly puts OVERFLOW/UNDERFLOW out of scope).
//
// ---------------------------------------------------------------------------
// CARRY4: agrees with UG474 with no simplification
// ---------------------------------------------------------------------------
//   UG474 describes the carry chain as, per bit i:
//       O[i]  = S[i] XOR C[i]
//       C[i+1] = S[i] ? C[i] : DI[i]
//   The mux form S ? C : DI is Boolean-identical to the form used here,
//   (S & C) | (~S & DI), so the two descriptions agree exactly.
//   CYINIT initialises the bottom CARRY4 of a chain; CIN carries the cascade
//   into every later block. Exactly one is active in valid RTL, which is why
//   C[0] = CYINIT | CIN is a faithful encoding rather than a shortcut.
//
// ---------------------------------------------------------------------------
// SRLC32E: agrees with UG474 apart from INIT
// ---------------------------------------------------------------------------
//   32-bit shift register, CE-gated, shifting on the rising clock edge;
//   Q reads the bit selected by the 5-bit address A; Q31 is the fixed bit-31
//   cascade output used to chain SRLs together.
//   Deviation: the real primitive takes an INIT parameter for initial
//   contents. The problem statement puts INIT parsing out of scope, so the
//   register always starts at zero here.
// ===========================================================================

// SPDX-License-Identifier: Apache-2.0
// Behavioural golden models for the three Xilinx primitives GEM must
// evaluate natively.
//
// These are written to be as LITERAL a transcription of the problem
// statement's equations as possible -- in particular CARRY4_ref is a genuine
// four-step ripple, and carry_chain_ref really does daisy-chain CO[3] into
// the next block's CI. They are intentionally NOT clever.
//
// The point of that is independence: csrc/gem_macros.cuh evaluates a fused
// carry chain as a single 64-bit add, and the whole verification argument is
// that the clever version and this literal version agree on random vectors.
// If both files shared an optimisation, the test would prove nothing.

`timescale 1ns / 1ps

// ---------------------------------------------------------------------------
// CARRY4 -- literal transcription of the silicon equations
// ---------------------------------------------------------------------------
//   C[0]   = CYINIT | CI
//   C[i+1] = (S[i] & C[i]) | (~S[i] & DI[i])
//   O[i]   = S[i] ^ C[i]
//   CO[i]  = C[i+1]
module CARRY4_ref (
    output [3:0] CO,
    output [3:0] O,
    input        CI,
    input        CYINIT,
    input  [3:0] DI,
    input  [3:0] S
);
    wire [4:0] C;
    assign C[0] = CYINIT | CI;

    genvar i;
    generate
        for (i = 0; i < 4; i = i + 1) begin : gen_bit
            assign C[i+1] = (S[i] & C[i]) | (~S[i] & DI[i]);
            assign O[i]   = S[i] ^ C[i];
            assign CO[i]  = C[i+1];
        end
    endgenerate
endmodule

// ---------------------------------------------------------------------------
// A cascade of NBLK CARRY4s, wired CO[3] -> CI exactly as a synthesiser would
// emit for a wide adder. This is the structure GEM must recognise and fuse.
// ---------------------------------------------------------------------------
module carry_chain_ref #(
    parameter NBLK = 15
) (
    output [4*NBLK-1:0] O,
    output [4*NBLK-1:0] CO,
    input               CYINIT,
    input  [4*NBLK-1:0] DI,
    input  [4*NBLK-1:0] S
);
    wire [NBLK:0] cc;
    assign cc[0] = 1'b0;

    genvar b;
    generate
        for (b = 0; b < NBLK; b = b + 1) begin : gen_blk
            CARRY4_ref u_c4 (
                .CO     (CO[4*b+3 -: 4]),
                .O      (O [4*b+3 -: 4]),
                // Block 0 takes the chain initialiser on CYINIT; every later
                // block takes the previous block's CO[3] on CI. Only one of
                // the two is ever active, per the problem statement.
                .CI     ((b == 0) ? 1'b0   : cc[b]),
                .CYINIT ((b == 0) ? CYINIT : 1'b0),
                .DI     (DI[4*b+3 -: 4]),
                .S      (S [4*b+3 -: 4])
            );
            assign cc[b+1] = CO[4*b+3];
        end
    endgenerate
endmodule

// ---------------------------------------------------------------------------
// DSP48E2 simplified subset
// ---------------------------------------------------------------------------
// AREG/BREG/CREG/DREG/ADREG/MREG = 0 (combinational), PREG = 1 (clocked).
//   AD     = use_pre ? A + D : A      (wraps at 27 bits)
//   M      = AD * B                   (45-bit signed)
//   P_next = state==0 ? C : state==1 ? M : P + M
module dsp48e2_ref (
    output reg signed [47:0] P,
    input                    clk,
    input      signed [26:0] A,
    input      signed [26:0] D,
    input      signed [17:0] B,
    input      signed [47:0] C,
    input             [1:0]  state,
    input                    use_pre
);
    // 27-bit pre-adder: the sum truncates back to 27 bits.
    wire signed [26:0] AD = use_pre ? (A + D) : A;
    // 27 x 18 -> 45 bit signed product.
    wire signed [44:0] M  = AD * B;

    reg signed [47:0] p_next;
    always @(*) begin
        case (state)
            2'd0:    p_next = C;        // bypass
            2'd1:    p_next = M;        // multiply only
            default: p_next = P + M;    // multiply-accumulate
        endcase
    end

    initial P = 48'd0;                  // registers initialise to zero
    always @(posedge clk) P <= p_next;
endmodule

// ---------------------------------------------------------------------------
// SRLC32E shift register LUT
// ---------------------------------------------------------------------------
//   on posedge, if CE: state <= {state[30:0], D}   (shift LSB -> MSB)
//   Q   = state[A]    combinational, dynamic address
//   Q31 = state[31]   combinational cascade output
module srlc32e_ref (
    output       Q,
    output       Q31,
    input        clk,
    input        CE,
    input        D,
    input  [4:0] A
);
    reg [31:0] state;
    initial state = 32'd0;              // registers initialise to zero

    assign Q   = state[A];
    assign Q31 = state[31];

    always @(posedge clk) begin
        if (CE) state <= {state[30:0], D};
    end
endmodule

build/gemdiff/tb_srlc32e.v
// Differential testbench: SRLC32E 32-bit shift register LUT.
// Per cycle: apply inputs, sample the COMBINATIONAL outputs against the
// current register contents, then clock and record the new register value.
`timescale 1ns/1ps
`include "xilinx_macros_ref.v"

module tb_srlc32e;
    reg        clk;
    reg        CE, D;
    reg  [4:0] A;
    wire       Q, Q31;

    srlc32e_ref u_srl (.Q(Q), .Q31(Q31), .clk(clk), .CE(CE), .D(D), .A(A));

    reg q_cap, q31_cap;
    integer fi, fo, n;

    // Waveform capture for inspection. Written under sim_out/,
    // never the repo root.
    initial begin
        $dumpfile("sim_out/tb_srlc32e.vcd");
        $dumpvars(0, tb_srlc32e);
    end

    initial begin
        clk = 1'b0;
        fi = $fopen("sim_out/stim_srl.txt", "r");
        fo = $fopen("sim_out/res_srl.txt", "w");
        if (fi == 0 || fo == 0) begin $display("FILE ERROR"); $finish; end

        n = $fscanf(fi, "%h %h %h\n", D, CE, A);
        while (n == 3) begin
            #1;                       // combinational read of CURRENT state
            q_cap   = Q;
            q31_cap = Q31;
            clk = 1'b1; #1;           // rising edge: shift happens
            clk = 1'b0; #1;
            // hierarchical peek at the register so the harness can compare
            // the full 32-bit state, not just the two output bits
            $fdisplay(fo, "%h %h %h", q_cap, q31_cap, u_srl.state);
            n = $fscanf(fi, "%h %h %h\n", D, CE, A);
        end
        $fclose(fi); $fclose(fo);
        $finish;
    end
endmodule

build/gemdiff/sim_out/tb_srlc32e.vcd
$date
	Wed Aug 26 20:51:46 2026
$end
$version
	Icarus Verilog
$end
$timescale
	1ps
$end
$scope module tb_srlc32e $end
$var wire 1 ! Q31 $end
$var wire 1 " Q $end
$var reg 5 # A [4:0] $end
$var reg 1 $ CE $end
$var reg 1 % D $end
$var reg 1 & clk $end
$var reg 1 ' q31_cap $end
$var reg 1 ( q_cap $end
$var integer 32 ) fi [31:0] $end
$var integer 32 * fo [31:0] $end
$var integer 32 + n [31:0] $end
$scope module u_srl $end
$var wire 5 , A [4:0] $end
$var wire 1 $ CE $end
$var wire 1 % D $end
$var wire 1 & clk $end
$var wire 1 ! Q31 $end
$var wire 1 " Q $end
$var reg 32 - state [31:0] $end
$upscope $end
$upscope $end
$enddefinitions $end
$comment Show the parameter values. $end
$dumpall
$end
#0
$dumpvars
b0 -
b0 ,
b11 +
b10000000000000000000000000000100 *
b10000000000000000000000000000011 )
x(
x'
0&
1%
1$
b0 #
0"
0!
$end
#1000
1"
b1 -
1&
0'
0(
#2000
0&
#3000
0"
b1 #
b1 ,
#4000
1"
b11 -
1&
#5000
0&
#6000
0"
b10 #
b10 ,
#7000
1"
b111 -
1&
#8000
0&
#9000
0"
b11 #
b11 ,
#10000
1"
b1111 -
1&
#11000
0&
#12000
0"
b100 #
b100 ,
#13000
1"
b11111 -
1&
#14000
0&
#15000
0"
b101 #
b101 ,
#16000
1"
b111111 -
1&
#17000
0&
#18000
0"
b110 #
b110 ,
#19000
1"
b1111111 -
1&
#20000
0&
#21000
0"
b111 #
b111 ,
#22000
1"
b11111111 -
1&
#23000
0&
#24000
0"
b1000 #
b1000 ,
#25000
1"
b111111111 -
1&
#26000
0&
#27000
0"
b1001 #
b1001 ,
#28000
1"
b1111111111 -
1&
#29000
0&
#30000
0"
b1010 #
b1010 ,
#31000
1"
b11111111111 -
1&
#32000
0&
#33000
0"
b1011 #
b1011 ,
#34000
1"
b111111111111 -
1&
#35000
0&
#36000
0"
b1100 #
b1100 ,
#37000
1"
b1111111111111 -
1&
#38000
0&
#39000
0"
b1101 #
b1101 ,
#40000
1"
b11111111111111 -
1&
#41000
0&
#42000
0"
b1110 #
b1110 ,
#43000
1"
b111111111111111 -
1&
#44000
0&
#45000
0"
b1111 #
b1111 ,
#46000
1"
b1111111111111111 -
1&
#47000
0&
#48000
0"
b10000 #
b10000 ,
#49000
1"
b11111111111111111 -
1&
#50000
0&
#51000
0"
b10001 #
b10001 ,
#52000
1"
b111111111111111111 -
1&
#53000
0&
#54000
0"
b10010 #
b10010 ,
#55000
1"
b1111111111111111111 -
1&
#56000
0&
#57000
0"
b10011 #
b10011 ,
#58000
1"
b11111111111111111111 -
1&
#59000
0&
#60000
0"
b10100 #
b10100 ,
#61000
1"
b111111111111111111111 -
1&
#62000
0&
#63000
0"
b10101 #
b10101 ,
#64000
1"
b1111111111111111111111 -
1&
#65000
0&
#66000
0"
b10110 #
b10110 ,
#67000
1"
b11111111111111111111111 -
1&
#68000
0&
#69000
0"
b10111 #
b10111 ,
#70000
1"
b111111111111111111111111 -
1&
#71000
0&
#72000
0"
b11000 #
b11000 ,
#73000
1"
b1111111111111111111111111 -
1&
#74000
0&
#75000
0"
b11001 #
b11001 ,
#76000
1"
b11111111111111111111111111 -
1&
#77000
0&
#78000
0"
b11010 #
b11010 ,
#79000
1"
b111111111111111111111111111 -
1&
#80000
0&
#81000
0"
b11011 #
b11011 ,
#82000
1"
b1111111111111111111111111111 -
1&
#83000
0&
#84000
0"
b11100 #
b11100 ,
#85000
1"
b11111111111111111111111111111 -
1&
#86000
0&
#87000
0"
b11101 #
b11101 ,
#88000
1"
b111111111111111111111111111111 -
1&
#89000
0&
#90000
0"
b11110 #
b11110 ,
#91000
1"
b1111111111111111111111111111111 -
1&
#92000
0&
#93000
0"
b11111 #
b11111 ,
#94000
1!
1"
b11111111111111111111111111111111 -
1&
#95000
0&
#96000
b0 #
b0 ,
0%
#97000
0"
b11111111111111111111111111111110 -
1&
1'
1(
#98000
0&
#99000
1"
b1 #
b1 ,
#100000
0"
b11111111111111111111111111111100 -
1&
#101000
0&
#102000
1"
b10 #
b10 ,
#103000
0"
b11111111111111111111111111111000 -
1&
#104000
0&
#105000
1"
b11 #
b11 ,
#106000
0"
b11111111111111111111111111110000 -
1&
#107000
0&
#108000
1"
b100 #
b100 ,
#109000
0"
b11111111111111111111111111100000 -
1&
#110000
0&
#111000
1"
b101 #
b101 ,
#112000
0"
b11111111111111111111111111000000 -
1&
#113000
0&
#114000
1"
b110 #
b110 ,
#115000
0"
b11111111111111111111111110000000 -
1&
#116000
0&
#117000
1"
b111 #
b111 ,
#118000
0"
b11111111111111111111111100000000 -
1&
#119000
0&
#120000
1"
b1000 #
b1000 ,
#121000
0"
b11111111111111111111111000000000 -
1&
#122000
0&
#123000
1"
b1001 #
b1001 ,
#124000
0"
b11111111111111111111110000000000 -
1&
#125000
0&
#126000
1"
b1010 #
b1010 ,
#127000
0"
b11111111111111111111100000000000 -
1&
#128000
0&
#129000
1"
b1011 #
b1011 ,
#130000
0"
b11111111111111111111000000000000 -
1&
#131000
0&
#132000
1"
b1100 #
b1100 ,
#133000
0"
b11111111111111111110000000000000 -
1&
#134000
0&
#135000
1"
b1101 #
b1101 ,
#136000
0"
b11111111111111111100000000000000 -
1&
#137000
0&
#138000
1"
b1110 #
b1110 ,
#139000
0"
b11111111111111111000000000000000 -
1&
#140000
0&
#141000
1"
b1111 #
b1111 ,
#142000
0"
b11111111111111110000000000000000 -
1&
#143000
0&
#144000
1"
b10000 #
b10000 ,
#145000
0"
b11111111111111100000000000000000 -
1&
#146000
0&
#147000
1"
b10001 #
b10001 ,
#148000
0"
b11111111111111000000000000000000 -
1&
#149000
0&
#150000
1"
b10010 #
b10010 ,
#151000
0"
b11111111111110000000000000000000 -
1&
#152000
0&
#153000
1"
b10011 #
b10011 ,
#154000
0"
b11111111111100000000000000000000 -
1&
#155000
0&
#156000
1"
b10100 #
b10100 ,
#157000
0"
b11111111111000000000000000000000 -
1&
#158000
0&
#159000
1"
b10101 #
b10101 ,
#160000
0"
b11111111110000000000000000000000 -
1&
#161000
0&
#162000
1"
b10110 #
b10110 ,
#163000
0"
b11111111100000000000000000000000 -
1&
#164000
0&
#165000
1"
b10111 #
b10111 ,
#166000
0"
b11111111000000000000000000000000 -
1&
#167000
0&
#168000
1"
b11000 #
b11000 ,
#169000
0"
b11111110000000000000000000000000 -
1&
#170000
0&
#171000
1"
b11001 #
b11001 ,
#172000
0"
b11111100000000000000000000000000 -
1&
#173000
0&
#174000
1"
b11010 #
b11010 ,
#175000
0"
b11111000000000000000000000000000 -
1&
#176000
0&
#177000
1"
b11011 #
b11011 ,
#178000
0"
b11110000000000000000000000000000 -
1&
#179000
0&
#180000
1"
b11100 #
b11100 ,
#181000
0"
b11100000000000000000000000000000 -
1&
#182000
0&
#183000
1"
b11101 #
b11101 ,
#184000
0"
b11000000000000000000000000000000 -
1&
#185000
0&
#186000
1"
b11110 #
b11110 ,
#187000
0"
b10000000000000000000000000000000 -
1&
#188000
0&
#189000
1"
b11111 #
b11111 ,
#190000
0!
0"
b0 -
1&
#191000
0&
#192000
b0 #
b0 ,
0$
1%
#193000
1&
0'
0(
#194000
0&
#195000
b1 #
b1 ,
#196000
1&
#197000
0&
#198000
b10 #
b10 ,
#199000
1&
#200000
0&
#201000
b11 #
b11 ,
#202000
1&
#203000
0&
#204000
b100 #
b100 ,
#205000
1&
#206000
0&
#207000
b101 #
b101 ,
#208000
1&
#209000
0&
#210000
b110 #
b110 ,
#211000
1&
#212000
0&
#213000
b111 #
b111 ,
#214000
1&
#215000
0&
#216000
b1000 #
b1000 ,
#217000
1&
#218000
0&
#219000
b1001 #
b1001 ,
#220000
1&
#221000
0&
#222000
b1010 #
b1010 ,
#223000
1&
#224000
0&
#225000
b1011 #
b1011 ,
#226000
1&
#227000
0&
#228000
b1100 #
b1100 ,
#229000
1&
#230000
0&
#231000
b1101 #
b1101 ,
#232000
1&
#233000
0&
#234000
b1110 #
b1110 ,
#235000
1&
#236000
0&
#237000
b1111 #
b1111 ,
#238000
1&
#239000
0&
#240000
b10000 #
b10000 ,
#241000
1&
#242000
0&
#243000
b10001 #
b10001 ,
#244000
1&
#245000
0&
#246000
b10010 #
b10010 ,
#247000
1&
#248000
0&
#249000
b10011 #
b10011 ,
#250000
1&
#251000
0&
#252000
b10100 #
b10100 ,
#253000
1&
#254000
0&
#255000
b10101 #
b10101 ,
#256000
1&
#257000
0&
#258000
b10110 #
b10110 ,
#259000
1&
#260000
0&
#261000
b10111 #
b10111 ,
#262000
1&
#263000
0&
#264000
b11000 #
b11000 ,
#265000
1&
#266000
0&
#267000
b11001 #
b11001 ,
#268000
1&
#269000
0&
#270000
b11010 #
b11010 ,
#271000
1&
#272000
0&
#273000
b11011 #
b11011 ,
#274000
1&
#275000
0&
#276000
b11100 #
b11100 ,
#277000
1&
#278000
0&
#279000
b11101 #
b11101 ,
#280000
1&
#281000
0&
#282000
b11110 #
b11110 ,
#283000
1&
#284000
0&
#285000
b11111 #
b11111 ,
#286000
1&
#287000
0&
#288000
1$
#289000
b1 -
1&
#290000
0&
#291000
0%
#292000
b10 -
1&
#293000
0&
#294000
b0 #
b0 ,
1%
#295000
1"
b101 -
1&
#296000
0&
#297000
0$
0%
#298000
1&
1(
#299000
0&
#300000
0"
b111 #
b111 ,
1%
#301000
1&
0(
#302000
0&
#303000
b11 #
b11 ,
#304000
1&
#305000
0&
#306000
b11011 #
b11011 ,
#307000
1&
#308000
0&
#309000
b11101 #
b11101 ,
1$
0%
#310000
b1010 -
1&
#311000
0&
#312000
b1011 #
b1011 ,
#313000
b10100 -
1&
#314000
0&
#315000
b10011 #
b10011 ,
1%
#316000
b101001 -
1&
#317000
0&
#318000
b11001 #
b11001 ,
0%
#319000
b1010010 -
1&
#320000
0&
#321000
b101 #
b101 ,
0$
1%
#322000
1&
#323000
0&
#324000
b10111 #
b10111 ,
1$
0%
#325000
b10100100 -
1&
#326000
0&
#327000
b11000 #
b11000 ,
0$
1%
#328000
1&
#329000
0&
#330000
b11001 #
b11001 ,
1$
0%
#331000
b101001000 -
1&
#332000
0&
#333000
b1010 #
b1010 ,
0$
1%
#334000
1&
#335000
0&
#336000
b11011 #
b11011 ,
0%
#337000
1&
#338000
0&
#339000
1"
b110 #
b110 ,
1%
#340000
1&
1(
#341000
0&
#342000
0"
b100 #
b100 ,
1$
0%
#343000
1"
b1010010000 -
1&
0(
#344000
0&
#345000
0"
b1000 #
b1000 ,
1%
#346000
1"
b10100100001 -
1&
#347000
0&
#348000
0"
b11011 #
b11011 ,
#349000
b101001000011 -
1&
#350000
0&
#351000
1"
b1001 #
b1001 ,
0%
#352000
0"
b1010010000110 -
1&
1(
#353000
0&
#354000
b110 #
b110 ,
0$
1%
#355000
1&
0(
#356000
0&
#357000
1"
b1 #
b1 ,
1$
0%
#358000
0"
b10100100001100 -
1&
1(
#359000
0&
#360000
b1100 #
b1100 ,
1%
#361000
1"
b101001000011001 -
1&
0(
#362000
0&
#363000
b1110 #
b1110 ,
0$
#364000
1&
1(
#365000
0&
#366000
0"
b10001 #
b10001 ,
#367000
1&
0(
#368000
0&
#369000
b10 #
b10 ,
1$
#370000
b1010010000110011 -
1&
#371000
0&
#372000
b11100 #
b11100 ,
0$
0%
#373000
1&
#374000
0&
#375000
b1100 #
b1100 ,
1%
#376000
1&
#377000
0&
#378000
1"
b1 #
b1 ,
1$
0%
#379000
b10100100001100110 -
1&
1(
#380000
0&
#381000
0"
b11110 #
b11110 ,
0$
1%
#382000
1&
0(
#383000
0&
#384000
1"
b10 #
b10 ,
#385000
1&
1(
#386000
0&
#387000
0"
b1111 #
b1111 ,
1$
#388000
1"
b101001000011001101 -
1&
0(
#389000
0&
#390000
0"
b11111 #
b11111 ,
0%
#391000
b1010010000110011010 -
1&
#392000
0&
#393000
1"
b1 #
b1 ,
#394000
0"
b10100100001100110100 -
1&
1(
#395000
0&
#396000
b1101 #
b1101 ,
0$
#397000
1&
0(
#398000
0&
#399000
1"
b1001 #
b1001 ,
1$
#400000
b101001000011001101000 -
1&
1(
#401000
0&
#402000
0"
b10000 #
b10000 ,
1%
#403000
1"
b1010010000110011010001 -
1&
0(
#404000
0&
#405000
0"
b1110 #
b1110 ,
#406000
b10100100001100110100011 -
1&
#407000
0&
#408000
1"
b1100 #
b1100 ,
0$
#409000
1&
1(
#410000
0&
#411000
b101 #
b101 ,
#412000
1&
#413000
0&
#414000
0"
b11000 #
b11000 ,
#415000
1&
0(
#416000
0&
#417000
1"
b1100 #
b1100 ,
1$
0%
#418000
b101001000011001101000110 -
1&
1(
#419000
0&
#420000
b10111 #
b10111 ,
0$
1%
#421000
1&
#422000
0&
#423000
0"
b100 #
b100 ,
#424000
1&
0(
#425000
0&
#426000
b10000 #
b10000 ,
#427000
1&
#428000
0&
#429000
b111 #
b111 ,
1$
#430000
1"
b1010010000110011010001101 -
1&
#431000
0&
#432000
0"
b1011 #
b1011 ,
0%
#433000
1"
b10100100001100110100011010 -
1&
#434000
0&
#435000
b11001 #
b11001 ,
#436000
0"
b101001000011001101000110100 -
1&
1(
#437000
0&
#438000
b11111 #
b11111 ,
0$
1%
#439000
1&
0(
#440000
0&
#441000
1"
b1001 #
b1001 ,
#442000
1&
1(
#443000
0&
#444000
0"
b0 #
b0 ,
1$
0%
#445000
b1010010000110011010001101000 -
1&
0(
#446000
0&
#447000
1"
b1100 #
b1100 ,
0$
#448000
1&
1(
#449000
0&
#450000
0"
b11010 #
b11010 ,
1$
1%
#451000
1"
b10100100001100110100011010001 -
1&
0(
#452000
0&
#453000
0"
b11110 #
b11110 ,
#454000
b101001000011001101000110100011 -
1&
#455000
0&
#456000
b1101 #
b1101 ,
#457000
1"
b1010010000110011010001101000111 -
1&
#458000
0&
#459000
0"
b11 #
b11 ,
0$
#460000
1&
#461000
0&
#462000
b100 #
b100 ,
0%
#463000
1&
#464000
0&
#465000
b10110 #
b10110 ,
1$
1%
#466000
1!
b10100100001100110100011010001111 -
1&
#467000
0&
#468000
1"
b11010 #
b11010 ,
#469000
0!
0"
b1001000011001101000110100011111 -
1&
1'
1(
#470000
0&
#471000
1"
b1010 #
b1010 ,
0$
#472000
1&
0'
#473000
0&
#474000
b0 #
b0 ,
0%
#475000
1&
#476000
0&
#477000
1$
#478000
1!
0"
b10010000110011010001101000111110 -
1&
#479000
0&
#480000
1"
b11100 #
b11100 ,
#481000
0!
0"
b100001100110100011010001111100 -
1&
1'
#482000
0&
#483000
b0 #
b0 ,
1%
#484000
1"
b1000011001101000110100011111001 -
1&
0'
0(
#485000
0&
#486000
0"
b11011 #
b11011 ,
#487000
1!
b10000110011010001101000111110011 -
1&
#488000
0&
#489000
0%
#490000
0!
1"
b1100110100011010001111100110 -
1&
1'
#491000
0&
#492000
0"
b1011 #
b1011 ,
1%
#493000
b11001101000110100011111001101 -
1&
0'
#494000
0&
#495000
1"
b0 #
b0 ,
0$
#496000
1&
1(
#497000
0&
#498000
0"
b10011 #
b10011 ,
1$
0%
#499000
b110011010001101000111110011010 -
1&
0(
#500000
0&
#501000
b110 #
b110 ,
0$
#502000
1&
#503000
0&
#504000
1"
b11000 #
b11000 ,
#505000
1&
1(
#506000
0&
#507000
0"
b11010 #
b11010 ,
1$
1%
#508000
1"
b1100110100011010001111100110101 -
1&
0(
#509000
0&
#510000
0"
b11111 #
b11111 ,
0%
#511000
1!
1"
b11001101000110100011111001101010 -
1&
#512000
0&
#513000
b1 #
b1 ,
#514000
0"
b10011010001101000111110011010100 -
1&
1'
1(
#515000
0&
#516000
b11 #
b11 ,
#517000
0!
1"
b110100011010001111100110101000 -
1&
0(
#518000
0&
#519000
b1011 #
b1011 ,
0$
1%
#520000
1&
0'
1(
#521000
0&
#522000
b10101 #
b10101 ,
#523000
1&
#524000
0&
#525000
b1100 #
b1100 ,
#526000
1&
#527000
0&
#528000
0"
b10100 #
b10100 ,
1$
0%
#529000
1"
b1101000110100011111001101010000 -
1&
0(
#530000
0&
#531000
b10111 #
b10111 ,
0$
#532000
1&
1(
#533000
0&
#534000
0"
b11100 #
b11100 ,
1$
1%
#535000
1!
1"
b11010001101000111110011010100001 -
1&
0(
#536000
0&
#537000
0"
b1 #
b1 ,
#538000
1"
b10100011010001111100110101000011 -
1&
1'
#539000
0&
#540000
0"
b1101 #
b1101 ,
0%
#541000
0!
b1000110100011111001101010000110 -
1&
#542000
0&
#543000
1"
b1001 #
b1001 ,
0$
1%
#544000
1&
0'
1(
#545000
0&
#546000
0"
b101 #
b101 ,
1$
0%
#547000
1!
b10001101000111110011010100001100 -
1&
0(
#548000
0&
#549000
1"
b10010 #
b10010 ,
#550000
0!
b11010001111100110101000011000 -
1&
1'
1(
#551000
0&
#552000
b11 #
b11 ,
1%
#553000
0"
b110100011111001101010000110001 -
1&
0'
#554000
0&
#555000
b1011 #
b1011 ,
#556000
1"
b1101000111110011010100001100011 -
1&
0(
#557000
0&
#558000
b10000 #
b10000 ,
0%
#559000
1!
b11010001111100110101000011000110 -
1&
1(
#560000
0&
#561000
b111 #
b111 ,
0$
1%
#562000
1&
1'
#563000
0&
#564000
b1110 #
b1110 ,
1$
0%
#565000
0"
b10100011111001101010000110001100 -
1&
#566000
0&
#567000
b1 #
b1 ,
#568000
0!
b1000111110011010100001100011000 -
1&
0(
#569000
0&
#570000
b11011 #
b11011 ,
0$
1%
#571000
1&
0'
#572000
0&
#573000
b1011 #
b1011 ,
0%
#574000
1&
#575000
0&
#576000
b101 #
b101 ,
#577000
1&
#578000
0&
#579000
1"
b11001 #
b11001 ,
#580000
1&
1(
#581000
0&
#582000
0"
b111 #
b111 ,
1%
#583000
1&
0(
#584000
0&
#585000
1"
b10000 #
b10000 ,
1$
#586000
1!
0"
b10001111100110101000011000110001 -
1&
1(
#587000
0&
#588000
b1100 #
b1100 ,
0%
#589000
0!
b11111001101010000110001100010 -
1&
1'
0(
#590000
0&
#591000
b11 #
b11 ,
1%
#592000
b111110011010100001100011000101 -
1&
0'
#593000
0&
#594000
1"
b11001 #
b11001 ,
0%
#595000
0"
b1111100110101000011000110001010 -
1&
1(
#596000
0&
#597000
1"
b10111 #
b10111 ,
1%
#598000
1!
b11111001101010000110001100010101 -
1&
#599000
0&
#600000
0"
b10000 #
b10000 ,
0%
#601000
b11110011010100001100011000101010 -
1&
1'
0(
#602000
0&
#603000
b10010 #
b10010 ,
0$
#604000
1&
#605000
0&
#606000
b10 #
b10 ,
1$
#607000
1"
b11100110101000011000110001010100 -
1&
#608000
0&
#609000
b1111 #
b1111 ,
1%
#610000
0"
b11001101010000110001100010101001 -
1&
1(
#611000
0&
#612000
b1001 #
b1001 ,
0$
#613000
1&
0(
#614000
0&
#615000
1"
b10000 #
b10000 ,
#616000
1&
1(
#617000
0&
#618000
0"
b1110 #
b1110 ,
#619000
1&
0(
#620000
0&
#621000
b100 #
b100 ,
1$
0%
#622000
1"
b10011010100001100011000101010010 -
1&
#623000
0&
#624000
0"
b1111 #
b1111 ,
0$
#625000
1&
#626000
0&
#627000
1"
b1101 #
b1101 ,
1$
#628000
0!
b110101000011000110001010100100 -
1&
1(
#629000
0&
#630000
b11010 #
b11010 ,
0$
1%
#631000
1&
0'
#632000
0&
#633000
0"
b10111 #
b10111 ,
1$
0%
#634000
b1101010000110001100010101001000 -
1&
0(
#635000
0&
#636000
b1011 #
b1011 ,
0$
1%
#637000
1&
#638000
0&
#639000
b1001 #
b1001 ,
1$
0%
#640000
1!
1"
b11010100001100011000101010010000 -
1&
#641000
0&
#642000
0"
b101 #
b101 ,
1%
#643000
1"
b10101000011000110001010100100001 -
1&
1'
#644000
0&
#645000
0"
b100 #
b100 ,
#646000
0!
b1010000110001100010101001000011 -
1&
#647000
0&
#648000
1"
b11100 #
b11100 ,
0%
#649000
1!
0"
b10100001100011000101010010000110 -
1&
0'
1(
#650000
0&
#651000
1"
b1 #
b1 ,
0$
1%
#652000
1&
1'
#653000
0&
#654000
0"
b1001 #
b1001 ,
1$
0%
#655000
0!
b1000011000110001010100100001100 -
1&
0(
#656000
0&
#657000
b1110 #
b1110 ,
#658000
1!
1"
b10000110001100010101001000011000 -
1&
0'
#659000
0&
#660000
b100 #
b100 ,
#661000
0!
b1100011000101010010000110000 -
1&
1'
1(
#662000
0&
#663000
0"
b11110 #
b11110 ,
0$
#664000
1&
0'
0(
#665000
0&
#666000
b1 #
b1 ,
1$
1%
#667000
b11000110001010100100001100001 -
1&
#668000
0&
#669000
1"
b10111 #
b10111 ,
0$
0%
#670000
1&
1(
#671000
0&
#672000
0"
b11010 #
b11010 ,
#673000
1&
0(
#674000
0&
#675000
b1100 #
b1100 ,
1%
#676000
1&
#677000
0&
#678000
1"
b11011 #
b11011 ,
1$
0%
#679000
0"
b110001100010101001000011000010 -
1&
1(
#680000
0&
#681000
1"
b110 #
b110 ,
0$
#682000
1&
#683000
0&
#684000
0"
b0 #
b0 ,
#685000
1&
0(
#686000
0&
#687000
1"
b1100 #
b1100 ,
1$
1%
#688000
0"
b1100011000101010010000110000101 -
1&
1(
#689000
0&
#690000
1"
b0 #
b0 ,
0%
#691000
1!
0"
b11000110001010100100001100001010 -
1&
#692000
0&
#693000
1"
b11110 #
b11110 ,
1%
#694000
0"
b10001100010101001000011000010101 -
1&
1'
#695000
0&
